{
  "dept": "MHCLG",
  "dept_id": "ministry_of_housing_communities_and_local_government",
  "year": 2024,
  "currency": "GBP",
  "total_dept": 46100000000,
  "total_spend25k": 38466111326,
  "partial": false,
  "months_covered": 12,
  "segments": [
    {
      "segment": "Local Govnmnt Resilience and Communities",
      "total": 16611049231,
      "transactions": 23542,
      "top_recipients": [
        {
          "rank": 1,
          "name": "OFFICE OF THE PAYMASTER GENERAL (NN",
          "type": "Contractor",
          "amount": 6976033051,
          "pct_of_segment": 42
        },
        {
          "rank": 2,
          "name": "GREATER LONDON AUTHORITY",
          "type": "Contractor",
          "amount": 340968117,
          "pct_of_segment": 2.05
        },
        {
          "rank": 3,
          "name": "BIRMINGHAM CITY CNCL",
          "type": "Contractor",
          "amount": 277191981,
          "pct_of_segment": 1.67
        },
        {
          "rank": 4,
          "name": "NORFOLK COUNTY COUNCIL",
          "type": "Local Authority",
          "amount": 148890953,
          "pct_of_segment": 0.9
        },
        {
          "rank": 5,
          "name": "LANCASHIRE COUNTY CNCL",
          "type": "Contractor",
          "amount": 146033550,
          "pct_of_segment": 0.88
        },
        {
          "rank": 6,
          "name": "LIVERPOOL CITY COUNCIL",
          "type": "Local Authority",
          "amount": 139019522,
          "pct_of_segment": 0.84
        },
        {
          "rank": 7,
          "name": "KENT COUNTY CNCL",
          "type": "Contractor",
          "amount": 132021047,
          "pct_of_segment": 0.79
        },
        {
          "rank": 8,
          "name": "ESSEX COUNTY CNCL",
          "type": "Contractor",
          "amount": 129511008,
          "pct_of_segment": 0.78
        },
        {
          "rank": 9,
          "name": "HAMPSHIRE COUNTY COUNCIL",
          "type": "Local Authority",
          "amount": 129026335,
          "pct_of_segment": 0.78
        },
        {
          "rank": 10,
          "name": "MANCHESTER CITY CNCL",
          "type": "Contractor",
          "amount": 113482499,
          "pct_of_segment": 0.68
        },
        {
          "rank": 11,
          "name": "LEEDS CITY CNCL",
          "type": "Contractor",
          "amount": 106974122,
          "pct_of_segment": 0.64
        },
        {
          "rank": 12,
          "name": "WESTMINSTER CITY CNCL",
          "type": "Contractor",
          "amount": 105898526,
          "pct_of_segment": 0.64
        },
        {
          "rank": 13,
          "name": "DURHAM COUNTY COUNCIL",
          "type": "Local Authority",
          "amount": 105244263,
          "pct_of_segment": 0.63
        },
        {
          "rank": 14,
          "name": "LONDON BOROUGH OF NEWHAM",
          "type": "Local Authority",
          "amount": 104258946,
          "pct_of_segment": 0.63
        },
        {
          "rank": 15,
          "name": "LEWISHAM LB",
          "type": "Contractor",
          "amount": 98473335,
          "pct_of_segment": 0.59
        },
        {
          "rank": 16,
          "name": "NOTTINGHAM CITY COUNCIL",
          "type": "Local Authority",
          "amount": 93519545,
          "pct_of_segment": 0.56
        },
        {
          "rank": 17,
          "name": "NOTTINGHAMSHIRE COUNTY CNCL",
          "type": "Contractor",
          "amount": 91155653,
          "pct_of_segment": 0.55
        },
        {
          "rank": 18,
          "name": "DERBYSHIRE COUNTYCOUNCIL",
          "type": "Contractor",
          "amount": 90158197,
          "pct_of_segment": 0.54
        },
        {
          "rank": 19,
          "name": "SANDWELL MBC",
          "type": "Contractor",
          "amount": 88151528,
          "pct_of_segment": 0.53
        },
        {
          "rank": 20,
          "name": "STAFFORDSHIRE COUNTY CNCL",
          "type": "Contractor",
          "amount": 86144963,
          "pct_of_segment": 0.52
        }
      ]
    },
    {
      "segment": "Local Government & Public Services",
      "total": 10772392947,
      "transactions": 7686,
      "top_recipients": [
        {
          "rank": 1,
          "name": "OFFICE OF THE PAYMASTER GENERAL (NN",
          "type": "Contractor",
          "amount": 3244208637,
          "pct_of_segment": 30.12
        },
        {
          "rank": 2,
          "name": "OFFICE OF THE  PAYMASTER GENERAL (C",
          "type": "Contractor",
          "amount": 1083500288,
          "pct_of_segment": 10.06
        },
        {
          "rank": 3,
          "name": "GREATER LONDON AUTHORITY",
          "type": "Contractor",
          "amount": 223707832,
          "pct_of_segment": 2.08
        },
        {
          "rank": 4,
          "name": "BIRMINGHAM CITY CNCL",
          "type": "Contractor",
          "amount": 208002796,
          "pct_of_segment": 1.93
        },
        {
          "rank": 5,
          "name": "NORFOLK COUNTY COUNCIL",
          "type": "Local Authority",
          "amount": 102913869,
          "pct_of_segment": 0.96
        },
        {
          "rank": 6,
          "name": "LANCASHIRE COUNTY CNCL",
          "type": "Contractor",
          "amount": 101212780,
          "pct_of_segment": 0.94
        },
        {
          "rank": 7,
          "name": "ESSEX COUNTY CNCL",
          "type": "Contractor",
          "amount": 94144392,
          "pct_of_segment": 0.87
        },
        {
          "rank": 8,
          "name": "LIVERPOOL CITY COUNCIL",
          "type": "Local Authority",
          "amount": 91038118,
          "pct_of_segment": 0.85
        },
        {
          "rank": 9,
          "name": "KENT COUNTY CNCL",
          "type": "Contractor",
          "amount": 90736852,
          "pct_of_segment": 0.84
        },
        {
          "rank": 10,
          "name": "HAMPSHIRE COUNTY COUNCIL",
          "type": "Local Authority",
          "amount": 89107591,
          "pct_of_segment": 0.83
        },
        {
          "rank": 11,
          "name": "NOTTINGHAM CITY COUNCIL",
          "type": "Local Authority",
          "amount": 85474935,
          "pct_of_segment": 0.79
        },
        {
          "rank": 12,
          "name": "DURHAM COUNTY COUNCIL",
          "type": "Local Authority",
          "amount": 85390604,
          "pct_of_segment": 0.79
        },
        {
          "rank": 13,
          "name": "MANCHESTER CITY CNCL",
          "type": "Contractor",
          "amount": 74976867,
          "pct_of_segment": 0.7
        },
        {
          "rank": 14,
          "name": "LONDON BOROUGH OF NEWHAM",
          "type": "Local Authority",
          "amount": 72838332,
          "pct_of_segment": 0.68
        },
        {
          "rank": 15,
          "name": "LEEDS CITY CNCL",
          "type": "Contractor",
          "amount": 71983795,
          "pct_of_segment": 0.67
        },
        {
          "rank": 16,
          "name": "LEWISHAM LB",
          "type": "Contractor",
          "amount": 64952751,
          "pct_of_segment": 0.6
        },
        {
          "rank": 17,
          "name": "NOTTINGHAMSHIRE COUNTY CNCL",
          "type": "Contractor",
          "amount": 63448817,
          "pct_of_segment": 0.59
        },
        {
          "rank": 18,
          "name": "SHEFFIELD CITY CNCL",
          "type": "Contractor",
          "amount": 62949114,
          "pct_of_segment": 0.58
        },
        {
          "rank": 19,
          "name": "STAFFORDSHIRE COUNTY CNCL",
          "type": "Contractor",
          "amount": 62250774,
          "pct_of_segment": 0.58
        },
        {
          "rank": 20,
          "name": "DERBYSHIRE COUNTYCOUNCIL",
          "type": "Contractor",
          "amount": 62153416,
          "pct_of_segment": 0.58
        }
      ]
    },
    {
      "segment": "Regeneration Housing and Planning",
      "total": 3163162338,
      "transactions": 3078,
      "top_recipients": [
        {
          "rank": 1,
          "name": "HOMES ENGLAND",
          "type": "Contractor",
          "amount": 1210000000,
          "pct_of_segment": 38.25
        },
        {
          "rank": 2,
          "name": "GREATER LONDON AUTHORITY",
          "type": "Contractor",
          "amount": 315229497,
          "pct_of_segment": 9.97
        },
        {
          "rank": 3,
          "name": "GTR MANCHESTER COMBINED AUTHORITY",
          "type": "Contractor",
          "amount": 75972097,
          "pct_of_segment": 2.4
        },
        {
          "rank": 4,
          "name": "ISLINGTON LB",
          "type": "Contractor",
          "amount": 65955307,
          "pct_of_segment": 2.09
        },
        {
          "rank": 5,
          "name": "BIRMINGHAM CITY CNCL",
          "type": "Contractor",
          "amount": 40314298,
          "pct_of_segment": 1.27
        },
        {
          "rank": 6,
          "name": "LEEDS CITY CNCL",
          "type": "Contractor",
          "amount": 39217801,
          "pct_of_segment": 1.24
        },
        {
          "rank": 7,
          "name": "MANCHESTER CITY CNCL",
          "type": "Contractor",
          "amount": 36436447,
          "pct_of_segment": 1.15
        },
        {
          "rank": 8,
          "name": "KENT COUNTY CNCL",
          "type": "Contractor",
          "amount": 34453795,
          "pct_of_segment": 1.09
        },
        {
          "rank": 9,
          "name": "EUROPEAN COMMISSION",
          "type": "Contractor",
          "amount": 33328414,
          "pct_of_segment": 1.05
        },
        {
          "rank": 10,
          "name": "LONDON BOROUGH OF ENFIELD",
          "type": "Local Authority",
          "amount": 26469751,
          "pct_of_segment": 0.84
        },
        {
          "rank": 11,
          "name": "OLDHAM MBC",
          "type": "Contractor",
          "amount": 22976979,
          "pct_of_segment": 0.73
        },
        {
          "rank": 12,
          "name": "LANCASHIRE COUNTY CNCL",
          "type": "Contractor",
          "amount": 21578780,
          "pct_of_segment": 0.68
        },
        {
          "rank": 13,
          "name": "HAMPSHIRE COUNTY COUNCIL",
          "type": "Local Authority",
          "amount": 18644108,
          "pct_of_segment": 0.59
        },
        {
          "rank": 14,
          "name": "ESSEX COUNTY CNCL",
          "type": "Contractor",
          "amount": 16672975,
          "pct_of_segment": 0.53
        },
        {
          "rank": 15,
          "name": "LONDON BOROUGH OF NEWHAM",
          "type": "Local Authority",
          "amount": 16643696,
          "pct_of_segment": 0.53
        },
        {
          "rank": 16,
          "name": "NOTTINGHAM CITY COUNCIL",
          "type": "Local Authority",
          "amount": 15286971,
          "pct_of_segment": 0.48
        },
        {
          "rank": 17,
          "name": "SALFORD CITY CNCL",
          "type": "Contractor",
          "amount": 15234204,
          "pct_of_segment": 0.48
        },
        {
          "rank": 18,
          "name": "CORNWALL UNITARY AUTHORITY",
          "type": "Contractor",
          "amount": 15195227,
          "pct_of_segment": 0.48
        },
        {
          "rank": 19,
          "name": "HARINGEY LB",
          "type": "Contractor",
          "amount": 15018533,
          "pct_of_segment": 0.47
        },
        {
          "rank": 20,
          "name": "SURREY COUNTY COUNCIL",
          "type": "Local Authority",
          "amount": 13628557,
          "pct_of_segment": 0.43
        }
      ]
    },
    {
      "segment": "Local Government Resilience &Communities",
      "total": 2691418425,
      "transactions": 2908,
      "top_recipients": [
        {
          "rank": 1,
          "name": "OFFICE OF THE PAYMASTER GENERAL (NN",
          "type": "Contractor",
          "amount": 1190641262,
          "pct_of_segment": 44.24
        },
        {
          "rank": 2,
          "name": "GREATER LONDON AUTHORITY",
          "type": "Contractor",
          "amount": 53142391,
          "pct_of_segment": 1.97
        },
        {
          "rank": 3,
          "name": "BIRMINGHAM CITY CNCL",
          "type": "Contractor",
          "amount": 43649222,
          "pct_of_segment": 1.62
        },
        {
          "rank": 4,
          "name": "LANCASHIRE COUNTY CNCL",
          "type": "Contractor",
          "amount": 26249343,
          "pct_of_segment": 0.98
        },
        {
          "rank": 5,
          "name": "NORFOLK COUNTY COUNCIL",
          "type": "Local Authority",
          "amount": 26197020,
          "pct_of_segment": 0.97
        },
        {
          "rank": 6,
          "name": "KENT COUNTY CNCL",
          "type": "Contractor",
          "amount": 23834690,
          "pct_of_segment": 0.89
        },
        {
          "rank": 7,
          "name": "LIVERPOOL CITY COUNCIL",
          "type": "Local Authority",
          "amount": 23259025,
          "pct_of_segment": 0.86
        },
        {
          "rank": 8,
          "name": "HAMPSHIRE COUNTY COUNCIL",
          "type": "Local Authority",
          "amount": 23171136,
          "pct_of_segment": 0.86
        },
        {
          "rank": 9,
          "name": "ESSEX COUNTY CNCL",
          "type": "Contractor",
          "amount": 23083936,
          "pct_of_segment": 0.86
        },
        {
          "rank": 10,
          "name": "MANCHESTER CITY CNCL",
          "type": "Contractor",
          "amount": 18112140,
          "pct_of_segment": 0.67
        },
        {
          "rank": 11,
          "name": "DURHAM COUNTY COUNCIL",
          "type": "Local Authority",
          "amount": 18008797,
          "pct_of_segment": 0.67
        },
        {
          "rank": 12,
          "name": "NOTTINGHAMSHIRE COUNTY CNCL",
          "type": "Contractor",
          "amount": 16510118,
          "pct_of_segment": 0.61
        },
        {
          "rank": 13,
          "name": "DERBYSHIRE COUNTYCOUNCIL",
          "type": "Contractor",
          "amount": 16424696,
          "pct_of_segment": 0.61
        },
        {
          "rank": 14,
          "name": "LEWISHAM LB",
          "type": "Contractor",
          "amount": 16364301,
          "pct_of_segment": 0.61
        },
        {
          "rank": 15,
          "name": "LEEDS CITY CNCL",
          "type": "Contractor",
          "amount": 16021732,
          "pct_of_segment": 0.6
        },
        {
          "rank": 16,
          "name": "LONDON BOROUGH OF NEWHAM",
          "type": "Local Authority",
          "amount": 15434675,
          "pct_of_segment": 0.57
        },
        {
          "rank": 17,
          "name": "SANDWELL MBC",
          "type": "Contractor",
          "amount": 15052388,
          "pct_of_segment": 0.56
        },
        {
          "rank": 18,
          "name": "STAFFORDSHIRE COUNTY CNCL",
          "type": "Contractor",
          "amount": 14780268,
          "pct_of_segment": 0.55
        },
        {
          "rank": 19,
          "name": "GREENWICH LB",
          "type": "Contractor",
          "amount": 14111455,
          "pct_of_segment": 0.52
        },
        {
          "rank": 20,
          "name": "WIRRAL MBC",
          "type": "Contractor",
          "amount": 13092426,
          "pct_of_segment": 0.49
        }
      ]
    },
    {
      "segment": "Levelling Up",
      "total": 2077218955,
      "transactions": 2202,
      "top_recipients": [
        {
          "rank": 1,
          "name": "Rhondda Cynon Taf County Council",
          "type": "Local Authority",
          "amount": 151643884,
          "pct_of_segment": 7.3
        },
        {
          "rank": 2,
          "name": "WEST MIDLANDS COMBINED AUTHORITY",
          "type": "Contractor",
          "amount": 100638878,
          "pct_of_segment": 4.84
        },
        {
          "rank": 3,
          "name": "GREATER LONDON AUTHORITY",
          "type": "Contractor",
          "amount": 92406066,
          "pct_of_segment": 4.45
        },
        {
          "rank": 4,
          "name": "North of Tyne Combined Authority",
          "type": "Contractor",
          "amount": 75371222,
          "pct_of_segment": 3.63
        },
        {
          "rank": 5,
          "name": "WEST YORKSHIRE COMBINED AUTHORITY",
          "type": "Contractor",
          "amount": 69550285,
          "pct_of_segment": 3.35
        },
        {
          "rank": 6,
          "name": "Cyngor Gwynedd",
          "type": "Contractor",
          "amount": 69120546,
          "pct_of_segment": 3.33
        },
        {
          "rank": 7,
          "name": "LIVERPOOL CITY REGION COMB AUTH",
          "type": "Contractor",
          "amount": 66402518,
          "pct_of_segment": 3.2
        },
        {
          "rank": 8,
          "name": "DERBYSHIRE COUNTY COUNCIL",
          "type": "Local Authority",
          "amount": 58334285,
          "pct_of_segment": 2.81
        },
        {
          "rank": 9,
          "name": "GREATER MANCHESTER COMBINED AUT",
          "type": "Contractor",
          "amount": 53617572,
          "pct_of_segment": 2.58
        },
        {
          "rank": 10,
          "name": "CAMBRIDGESHIRE COUNTY COUNCIL",
          "type": "Local Authority",
          "amount": 47200000,
          "pct_of_segment": 2.27
        },
        {
          "rank": 11,
          "name": "South Yorkshire Mayoral Combined",
          "type": "Contractor",
          "amount": 42873833,
          "pct_of_segment": 2.06
        },
        {
          "rank": 12,
          "name": "WEST OF ENGLAND COMBINED AUTHORITY",
          "type": "Contractor",
          "amount": 37399012,
          "pct_of_segment": 1.8
        },
        {
          "rank": 13,
          "name": "GTR MANCHESTER COMBINED AUTHORITY",
          "type": "Contractor",
          "amount": 36484285,
          "pct_of_segment": 1.76
        },
        {
          "rank": 14,
          "name": "TEES VALLEY COMBINED AUTHORITY",
          "type": "Contractor",
          "amount": 35569433,
          "pct_of_segment": 1.71
        },
        {
          "rank": 15,
          "name": "York & North Yorkshire Combined Aut",
          "type": "Contractor",
          "amount": 33580738,
          "pct_of_segment": 1.62
        },
        {
          "rank": 16,
          "name": "NORTH EAST COMBINED AUTHORITY",
          "type": "Contractor",
          "amount": 28350285,
          "pct_of_segment": 1.36
        },
        {
          "rank": 17,
          "name": "Cumberland Council",
          "type": "Local Authority",
          "amount": 27073841,
          "pct_of_segment": 1.3
        },
        {
          "rank": 18,
          "name": "SHEFFIELD CITY REGION COMB AUTH",
          "type": "Contractor",
          "amount": 25901859,
          "pct_of_segment": 1.25
        },
        {
          "rank": 19,
          "name": "GATESHEAD MBC",
          "type": "Contractor",
          "amount": 25195032,
          "pct_of_segment": 1.21
        },
        {
          "rank": 20,
          "name": "TORBAY BC",
          "type": "Contractor",
          "amount": 21832794,
          "pct_of_segment": 1.05
        }
      ]
    },
    {
      "segment": "Local Growth, Communities and Devolution",
      "total": 1410497536,
      "transactions": 1046,
      "top_recipients": [
        {
          "rank": 1,
          "name": "CORNWALL UNITARY AUTHORITY",
          "type": "Contractor",
          "amount": 103047955,
          "pct_of_segment": 7.31
        },
        {
          "rank": 2,
          "name": "WEST YORKSHIRE COMBINED AUTHORITY",
          "type": "Contractor",
          "amount": 44207362,
          "pct_of_segment": 3.13
        },
        {
          "rank": 3,
          "name": "Glasgow CC",
          "type": "Contractor",
          "amount": 43697671,
          "pct_of_segment": 3.1
        },
        {
          "rank": 4,
          "name": "City and County of Swansea",
          "type": "Contractor",
          "amount": 37611301,
          "pct_of_segment": 2.67
        },
        {
          "rank": 5,
          "name": "ROTHERHAM MBC",
          "type": "Contractor",
          "amount": 28172148,
          "pct_of_segment": 2
        },
        {
          "rank": 6,
          "name": "NORTH EAST COMBINED AUTHORITY",
          "type": "Contractor",
          "amount": 25000000,
          "pct_of_segment": 1.77
        },
        {
          "rank": 7,
          "name": "THURROCK BC",
          "type": "Contractor",
          "amount": 24970242,
          "pct_of_segment": 1.77
        },
        {
          "rank": 8,
          "name": "HULL CITY COUNCIL",
          "type": "Local Authority",
          "amount": 24600000,
          "pct_of_segment": 1.74
        },
        {
          "rank": 9,
          "name": "NORTH EAST LINCOLNSHIRE COUNCIL",
          "type": "Local Authority",
          "amount": 22965500,
          "pct_of_segment": 1.63
        },
        {
          "rank": 10,
          "name": "LIVERPOOL CITY COUNCIL",
          "type": "Local Authority",
          "amount": 22000000,
          "pct_of_segment": 1.56
        },
        {
          "rank": 11,
          "name": "STOKE ON TRENT CITY COUNCIL",
          "type": "Local Authority",
          "amount": 20549604,
          "pct_of_segment": 1.46
        },
        {
          "rank": 12,
          "name": "TENDRING DISTRICT COUNCIL",
          "type": "Local Authority",
          "amount": 20390000,
          "pct_of_segment": 1.45
        },
        {
          "rank": 13,
          "name": "LINCOLNSHIRE CC",
          "type": "Contractor",
          "amount": 20000000,
          "pct_of_segment": 1.42
        },
        {
          "rank": 14,
          "name": "LANCASHIRE COUNTY COUNCIL",
          "type": "Local Authority",
          "amount": 20000000,
          "pct_of_segment": 1.42
        },
        {
          "rank": 15,
          "name": "BOSTON BC",
          "type": "Contractor",
          "amount": 18728536,
          "pct_of_segment": 1.33
        },
        {
          "rank": 16,
          "name": "LEICESTERSHIRE COUNTY COUNCIL",
          "type": "Local Authority",
          "amount": 18265000,
          "pct_of_segment": 1.29
        },
        {
          "rank": 17,
          "name": "NUNEATON & BEDWORTH BC",
          "type": "Contractor",
          "amount": 17474288,
          "pct_of_segment": 1.24
        },
        {
          "rank": 18,
          "name": "City of Wolverhampton Council",
          "type": "Local Authority",
          "amount": 16131829,
          "pct_of_segment": 1.14
        },
        {
          "rank": 19,
          "name": "DEVON COUNTY COUNCIL",
          "type": "Local Authority",
          "amount": 16000000,
          "pct_of_segment": 1.13
        },
        {
          "rank": 20,
          "name": "DONCASTER MBC",
          "type": "Contractor",
          "amount": 15896657,
          "pct_of_segment": 1.13
        }
      ]
    },
    {
      "segment": "Regeneration, Housing and Planning",
      "total": 748178864,
      "transactions": 431,
      "top_recipients": [
        {
          "rank": 1,
          "name": "HOMES ENGLAND",
          "type": "Contractor",
          "amount": 370000000,
          "pct_of_segment": 49.45
        },
        {
          "rank": 2,
          "name": "GREATER LONDON AUTHORITY",
          "type": "Contractor",
          "amount": 266476984,
          "pct_of_segment": 35.62
        },
        {
          "rank": 3,
          "name": "WILTSHIRE COUNCIL",
          "type": "Local Authority",
          "amount": 13050318,
          "pct_of_segment": 1.74
        },
        {
          "rank": 4,
          "name": "BROADLAND DC",
          "type": "Contractor",
          "amount": 10222610,
          "pct_of_segment": 1.37
        },
        {
          "rank": 5,
          "name": "FAREHAM BC",
          "type": "Contractor",
          "amount": 10222610,
          "pct_of_segment": 1.37
        },
        {
          "rank": 6,
          "name": "GREENWICH LB",
          "type": "Contractor",
          "amount": 7906647,
          "pct_of_segment": 1.06
        },
        {
          "rank": 7,
          "name": "DORSET COUNTY COUNCIL",
          "type": "Local Authority",
          "amount": 4730000,
          "pct_of_segment": 0.63
        },
        {
          "rank": 8,
          "name": "EBBSFLEET DEVELOPMENT CORPORATION",
          "type": "Contractor",
          "amount": 3500000,
          "pct_of_segment": 0.47
        },
        {
          "rank": 9,
          "name": "CORNWALL COUNCIL",
          "type": "Local Authority",
          "amount": 3207648,
          "pct_of_segment": 0.43
        },
        {
          "rank": 10,
          "name": "RICHMOND UPON THAMES LB",
          "type": "Contractor",
          "amount": 2977520,
          "pct_of_segment": 0.4
        },
        {
          "rank": 11,
          "name": "WYCHAVON DISTRICT COUNCIL",
          "type": "Local Authority",
          "amount": 2015400,
          "pct_of_segment": 0.27
        },
        {
          "rank": 12,
          "name": "HAVANT BC",
          "type": "Contractor",
          "amount": 1905897,
          "pct_of_segment": 0.25
        },
        {
          "rank": 13,
          "name": "LONDON BOROUGH OF ENFIELD",
          "type": "Local Authority",
          "amount": 1850807,
          "pct_of_segment": 0.25
        },
        {
          "rank": 14,
          "name": "HUNTINGDONSHIRE DC",
          "type": "Contractor",
          "amount": 1836041,
          "pct_of_segment": 0.25
        },
        {
          "rank": 15,
          "name": "LONDON BOROUGH OF HACKNEY",
          "type": "Local Authority",
          "amount": 1672861,
          "pct_of_segment": 0.22
        },
        {
          "rank": 16,
          "name": "FALMOUTH UNIVERSITY",
          "type": "University",
          "amount": 1548085,
          "pct_of_segment": 0.21
        },
        {
          "rank": 17,
          "name": "LIVERPOOL CITY COUNCIL",
          "type": "Local Authority",
          "amount": 1516063,
          "pct_of_segment": 0.2
        },
        {
          "rank": 18,
          "name": "CAMBS & PETERBOROUGH COMB AUT",
          "type": "Contractor",
          "amount": 1439298,
          "pct_of_segment": 0.19
        },
        {
          "rank": 19,
          "name": "BASINGSTOKE & DEANE BC",
          "type": "Contractor",
          "amount": 1392345,
          "pct_of_segment": 0.19
        },
        {
          "rank": 20,
          "name": "MALVERN HILLS DC",
          "type": "Contractor",
          "amount": 1355805,
          "pct_of_segment": 0.18
        }
      ]
    },
    {
      "segment": "Safer and Greener Buildings",
      "total": 551375832,
      "transactions": 1403,
      "top_recipients": [
        {
          "rank": 1,
          "name": "HOMES ENGLAND",
          "type": "Contractor",
          "amount": 240583135,
          "pct_of_segment": 43.63
        },
        {
          "rank": 2,
          "name": "GREATER LONDON AUTHORITY",
          "type": "Contractor",
          "amount": 213095558,
          "pct_of_segment": 38.65
        },
        {
          "rank": 3,
          "name": "BUSINESS INNOVATION & SKILLS",
          "type": "Contractor",
          "amount": 12246132,
          "pct_of_segment": 2.22
        },
        {
          "rank": 4,
          "name": "ROYAL BOROUGH  KENSINGTON & CHELSEA",
          "type": "Local Authority",
          "amount": 8302232,
          "pct_of_segment": 1.51
        },
        {
          "rank": 5,
          "name": "Riverside Group Limited",
          "type": "Contractor",
          "amount": 6246792,
          "pct_of_segment": 1.13
        },
        {
          "rank": 6,
          "name": "ATKINSRÉALIS PPS LIMITED",
          "type": "Contractor",
          "amount": 5605324,
          "pct_of_segment": 1.02
        },
        {
          "rank": 7,
          "name": "Peabody Trust",
          "type": "Contractor",
          "amount": 5221075,
          "pct_of_segment": 0.95
        },
        {
          "rank": 8,
          "name": "LABC",
          "type": "Contractor",
          "amount": 5096390,
          "pct_of_segment": 0.92
        },
        {
          "rank": 9,
          "name": "Deconstruct Uk Ltd",
          "type": "Contractor",
          "amount": 4920534,
          "pct_of_segment": 0.89
        },
        {
          "rank": 10,
          "name": "Mattison Scaffolding Ltd.",
          "type": "Contractor",
          "amount": 4440000,
          "pct_of_segment": 0.81
        },
        {
          "rank": 11,
          "name": "SCOR UK Company Limited",
          "type": "Contractor",
          "amount": 2767320,
          "pct_of_segment": 0.5
        },
        {
          "rank": 12,
          "name": "DELOITTE  LLP",
          "type": "Consultancy",
          "amount": 2475241,
          "pct_of_segment": 0.45
        },
        {
          "rank": 13,
          "name": "Notting Hill Home Ownership Ltd",
          "type": "Contractor",
          "amount": 2468765,
          "pct_of_segment": 0.45
        },
        {
          "rank": 14,
          "name": "LOCAL GOVERNMENT ASSOCIATION",
          "type": "Contractor",
          "amount": 1905083,
          "pct_of_segment": 0.35
        },
        {
          "rank": 15,
          "name": "GOVERNMENT LEGAL DEPARTMENT",
          "type": "Contractor",
          "amount": 1728906,
          "pct_of_segment": 0.31
        },
        {
          "rank": 16,
          "name": "Notting Hill Genesis",
          "type": "Contractor",
          "amount": 1566362,
          "pct_of_segment": 0.28
        },
        {
          "rank": 17,
          "name": "WALKER MORRIS LLP",
          "type": "Contractor",
          "amount": 1503117,
          "pct_of_segment": 0.27
        },
        {
          "rank": 18,
          "name": "Network Homes Limited????",
          "type": "Contractor",
          "amount": 1414745,
          "pct_of_segment": 0.26
        },
        {
          "rank": 19,
          "name": "Swan Housing Association",
          "type": "Contractor",
          "amount": 1072744,
          "pct_of_segment": 0.19
        },
        {
          "rank": 20,
          "name": "A2DOMINION GROUP",
          "type": "Contractor",
          "amount": 1032482,
          "pct_of_segment": 0.19
        }
      ]
    },
    {
      "segment": "CFO and Corporate",
      "total": 239876184,
      "transactions": 4370,
      "top_recipients": [
        {
          "rank": 1,
          "name": "DLUHC PAYROLL ACCOUNT",
          "type": "Contractor",
          "amount": 77344401,
          "pct_of_segment": 32.24
        },
        {
          "rank": 2,
          "name": "GOVERNMENT PROPERTY AGENCY",
          "type": "Contractor",
          "amount": 52327116,
          "pct_of_segment": 21.81
        },
        {
          "rank": 3,
          "name": "GOVERNMENT LEGAL DEPARTMENT",
          "type": "Contractor",
          "amount": 15478388,
          "pct_of_segment": 6.45
        },
        {
          "rank": 4,
          "name": "PHOENIX SOFTWARE LTD",
          "type": "Contractor",
          "amount": 8873569,
          "pct_of_segment": 3.7
        },
        {
          "rank": 5,
          "name": "NATIONAL CENTRE FOR SOCIAL RESEARCH",
          "type": "Contractor",
          "amount": 8625018,
          "pct_of_segment": 3.6
        },
        {
          "rank": 6,
          "name": "County HR Solutions Ltd T/A CHR Sol",
          "type": "Contractor",
          "amount": 8556967,
          "pct_of_segment": 3.57
        },
        {
          "rank": 7,
          "name": "TPXimpact Limited",
          "type": "Contractor",
          "amount": 7768173,
          "pct_of_segment": 3.24
        },
        {
          "rank": 8,
          "name": "CABINET OFFICE HR SHARED SERVICES",
          "type": "Contractor",
          "amount": 5567673,
          "pct_of_segment": 2.32
        },
        {
          "rank": 9,
          "name": "ALEXANDER MANN SOLUTIONS LTD",
          "type": "Contractor",
          "amount": 3609670,
          "pct_of_segment": 1.5
        },
        {
          "rank": 10,
          "name": "AirWalk Consulting Reply Ltd",
          "type": "Contractor",
          "amount": 3582001,
          "pct_of_segment": 1.49
        },
        {
          "rank": 11,
          "name": "ARCULUS CYBER SECURITY LTD",
          "type": "Contractor",
          "amount": 3455367,
          "pct_of_segment": 1.44
        },
        {
          "rank": 12,
          "name": "X M A LTD",
          "type": "Contractor",
          "amount": 3266060,
          "pct_of_segment": 1.36
        },
        {
          "rank": 13,
          "name": "MANNING GOTTLIEB OMD",
          "type": "Contractor",
          "amount": 2959973,
          "pct_of_segment": 1.23
        },
        {
          "rank": 14,
          "name": "DELOITTE MCS LTD",
          "type": "Consultancy",
          "amount": 2251914,
          "pct_of_segment": 0.94
        },
        {
          "rank": 15,
          "name": "UBDS IT Consulting Limited",
          "type": "Contractor",
          "amount": 2167901,
          "pct_of_segment": 0.9
        },
        {
          "rank": 16,
          "name": "HM TREASURY",
          "type": "Contractor",
          "amount": 2061394,
          "pct_of_segment": 0.86
        },
        {
          "rank": 17,
          "name": "IMPROVEMENT & DEVELOPMENT AGENCY",
          "type": "Contractor",
          "amount": 2000000,
          "pct_of_segment": 0.83
        },
        {
          "rank": 18,
          "name": "MADE TECH LTD",
          "type": "Contractor",
          "amount": 1691401,
          "pct_of_segment": 0.71
        },
        {
          "rank": 19,
          "name": "SOFTWIRE TECHNOLOGY LTD",
          "type": "Contractor",
          "amount": 1657684,
          "pct_of_segment": 0.69
        },
        {
          "rank": 20,
          "name": "Livtech Solutions Ltd",
          "type": "Contractor",
          "amount": 1545906,
          "pct_of_segment": 0.64
        }
      ]
    },
    {
      "segment": "Regeneration",
      "total": 187053718,
      "transactions": 753,
      "top_recipients": [
        {
          "rank": 1,
          "name": "WEST MIDLANDS COMBINED AUTHORITY",
          "type": "Contractor",
          "amount": 33000000,
          "pct_of_segment": 17.64
        },
        {
          "rank": 2,
          "name": "TEES VALLEY COMBINED AUTHORITY",
          "type": "Contractor",
          "amount": 5871008,
          "pct_of_segment": 3.14
        },
        {
          "rank": 3,
          "name": "KENT COUNTY COUNCIL",
          "type": "Local Authority",
          "amount": 4287461,
          "pct_of_segment": 2.29
        },
        {
          "rank": 4,
          "name": "CORNWALL UNITARY AUTHORITY",
          "type": "Contractor",
          "amount": 3767426,
          "pct_of_segment": 2.01
        },
        {
          "rank": 5,
          "name": "SOLIHULL MBC",
          "type": "Contractor",
          "amount": 3541488,
          "pct_of_segment": 1.89
        },
        {
          "rank": 6,
          "name": "EBBSFLEET DEVELOPMENT CORPORATION",
          "type": "Contractor",
          "amount": 3500000,
          "pct_of_segment": 1.87
        },
        {
          "rank": 7,
          "name": "CENTRAL BEDFORDSHIRE COUNCIL",
          "type": "Local Authority",
          "amount": 3455235,
          "pct_of_segment": 1.85
        },
        {
          "rank": 8,
          "name": "LEEDS CITY CNCL",
          "type": "Contractor",
          "amount": 3445225,
          "pct_of_segment": 1.84
        },
        {
          "rank": 9,
          "name": "SALFORD CITY CNCL",
          "type": "Contractor",
          "amount": 2866209,
          "pct_of_segment": 1.53
        },
        {
          "rank": 10,
          "name": "DURHAM COUNTY COUNCIL",
          "type": "Local Authority",
          "amount": 2863048,
          "pct_of_segment": 1.53
        },
        {
          "rank": 11,
          "name": "BIRMINGHAM CITY COUNCIL",
          "type": "Local Authority",
          "amount": 2822052,
          "pct_of_segment": 1.51
        },
        {
          "rank": 12,
          "name": "SHROPSHIRE UNITARY AUTHORITY",
          "type": "Contractor",
          "amount": 2686317,
          "pct_of_segment": 1.44
        },
        {
          "rank": 13,
          "name": "STRATFORD ON AVON DC",
          "type": "Contractor",
          "amount": 2114430,
          "pct_of_segment": 1.13
        },
        {
          "rank": 14,
          "name": "GREATER LONDON AUTHORITY",
          "type": "Contractor",
          "amount": 2039058,
          "pct_of_segment": 1.09
        },
        {
          "rank": 15,
          "name": "BRENT LB",
          "type": "Contractor",
          "amount": 1978279,
          "pct_of_segment": 1.06
        },
        {
          "rank": 16,
          "name": "PETERBOROUGH CITY CNCL",
          "type": "Contractor",
          "amount": 1857565,
          "pct_of_segment": 0.99
        },
        {
          "rank": 17,
          "name": "NOTTINGHAM CITY COUNCIL",
          "type": "Local Authority",
          "amount": 1857163,
          "pct_of_segment": 0.99
        },
        {
          "rank": 18,
          "name": "CORNWALL DEVELOPMENT COMPANY",
          "type": "Contractor",
          "amount": 1670998,
          "pct_of_segment": 0.89
        },
        {
          "rank": 19,
          "name": "FENLAND DC",
          "type": "Contractor",
          "amount": 1660283,
          "pct_of_segment": 0.89
        },
        {
          "rank": 20,
          "name": "MANCHESTER CITY CNCL",
          "type": "Contractor",
          "amount": 1659175,
          "pct_of_segment": 0.89
        }
      ]
    },
    {
      "segment": "Resettlements",
      "total": 9628781,
      "transactions": 194,
      "top_recipients": [
        {
          "rank": 1,
          "name": "Central British Fund World Jewish R",
          "type": "Contractor",
          "amount": 1702425,
          "pct_of_segment": 17.68
        },
        {
          "rank": 2,
          "name": "PALANTIR TECHNOLOGIES UK LTD",
          "type": "Contractor",
          "amount": 1250000,
          "pct_of_segment": 12.98
        },
        {
          "rank": 3,
          "name": "Citizens Uk Charity",
          "type": "Contractor",
          "amount": 396000,
          "pct_of_segment": 4.11
        },
        {
          "rank": 4,
          "name": "GREATER LONDON AUTHORITY",
          "type": "Contractor",
          "amount": 345204,
          "pct_of_segment": 3.59
        },
        {
          "rank": 5,
          "name": "SALFORD CITY COUNCIL",
          "type": "Local Authority",
          "amount": 317900,
          "pct_of_segment": 3.3
        },
        {
          "rank": 6,
          "name": "Barnardos",
          "type": "Contractor",
          "amount": 300000,
          "pct_of_segment": 3.12
        },
        {
          "rank": 7,
          "name": "Path Yorkshire (Ltd)",
          "type": "Contractor",
          "amount": 260755,
          "pct_of_segment": 2.71
        },
        {
          "rank": 8,
          "name": "WOKINGHAM DC",
          "type": "Contractor",
          "amount": 209361,
          "pct_of_segment": 2.17
        },
        {
          "rank": 9,
          "name": "MANCHESTER CITY COUNCIL",
          "type": "Local Authority",
          "amount": 209077,
          "pct_of_segment": 2.17
        },
        {
          "rank": 10,
          "name": "Association Of Ukrainians In GB Ltd",
          "type": "Contractor",
          "amount": 200000,
          "pct_of_segment": 2.08
        },
        {
          "rank": 11,
          "name": "SE STRATEGIC PARTNERSHIP FOR MIGRAT",
          "type": "Contractor",
          "amount": 196000,
          "pct_of_segment": 2.04
        },
        {
          "rank": 12,
          "name": "TRAFFORD MBC",
          "type": "Contractor",
          "amount": 189550,
          "pct_of_segment": 1.97
        },
        {
          "rank": 13,
          "name": "MADE TECH LTD",
          "type": "Contractor",
          "amount": 185063,
          "pct_of_segment": 1.92
        },
        {
          "rank": 14,
          "name": "St Mary's Ukrainian School Ltd",
          "type": "Contractor",
          "amount": 182269,
          "pct_of_segment": 1.89
        },
        {
          "rank": 15,
          "name": "LEEDS CITY COUNCIL",
          "type": "Local Authority",
          "amount": 172883,
          "pct_of_segment": 1.8
        },
        {
          "rank": 16,
          "name": "City of Wolverhampton Council",
          "type": "Local Authority",
          "amount": 149464,
          "pct_of_segment": 1.55
        },
        {
          "rank": 17,
          "name": "READING BC",
          "type": "Contractor",
          "amount": 140250,
          "pct_of_segment": 1.46
        },
        {
          "rank": 18,
          "name": "Hong Kong Well UK CIC",
          "type": "Contractor",
          "amount": 139225,
          "pct_of_segment": 1.45
        },
        {
          "rank": 19,
          "name": "CONVENTION OF SCOTTISH LOCAL AUTH",
          "type": "Contractor",
          "amount": 121000,
          "pct_of_segment": 1.26
        },
        {
          "rank": 20,
          "name": "BRADFORD FOUNDATION TRUST",
          "type": "Contractor",
          "amount": 119801,
          "pct_of_segment": 1.24
        }
      ]
    },
    {
      "segment": "Union & Windsor Framework",
      "total": 1805981,
      "transactions": 31,
      "top_recipients": [
        {
          "rank": 1,
          "name": "EUROPEAN MARINE ENERGY CENTRE LTD",
          "type": "Contractor",
          "amount": 1494861,
          "pct_of_segment": 82.77
        },
        {
          "rank": 2,
          "name": "CABINET OFFICE HR SHARED SERVICES",
          "type": "Contractor",
          "amount": 142470,
          "pct_of_segment": 7.89
        },
        {
          "rank": 3,
          "name": "KANTAR PUBLIC UK LTD",
          "type": "Contractor",
          "amount": 73670,
          "pct_of_segment": 4.08
        },
        {
          "rank": 4,
          "name": "SCOTLAND OFFICE",
          "type": "Contractor",
          "amount": 38603,
          "pct_of_segment": 2.14
        },
        {
          "rank": 5,
          "name": "CORPORATE TRAVEL MANAGEMENT(NORTH)L",
          "type": "Contractor",
          "amount": 31566,
          "pct_of_segment": 1.75
        },
        {
          "rank": 6,
          "name": "CALDER CONFERENCES  LTD",
          "type": "Contractor",
          "amount": 17818,
          "pct_of_segment": 0.99
        },
        {
          "rank": 7,
          "name": "KPMG LLP (CSL)",
          "type": "Consultancy",
          "amount": 5909,
          "pct_of_segment": 0.33
        },
        {
          "rank": 8,
          "name": "Lochs Motor Transport Ltd",
          "type": "Contractor",
          "amount": 420,
          "pct_of_segment": 0.02
        },
        {
          "rank": 9,
          "name": "Employee Expenses",
          "type": "Contractor",
          "amount": 349,
          "pct_of_segment": 0.02
        },
        {
          "rank": 10,
          "name": "CYMEN CYF",
          "type": "Contractor",
          "amount": 247,
          "pct_of_segment": 0.01
        },
        {
          "rank": 11,
          "name": "EQUANS E&S Solutions Limited",
          "type": "Contractor",
          "amount": 68,
          "pct_of_segment": 0
        }
      ]
    },
    {
      "segment": "Strategy and Communications",
      "total": 1162630,
      "transactions": 10,
      "top_recipients": [
        {
          "rank": 1,
          "name": "TPXimpact Limited",
          "type": "Contractor",
          "amount": 887812,
          "pct_of_segment": 76.36
        },
        {
          "rank": 2,
          "name": "OFFICE FOR NATIONAL STATISTICS",
          "type": "Contractor",
          "amount": 156583,
          "pct_of_segment": 13.47
        },
        {
          "rank": 3,
          "name": "CABINET OFFICE",
          "type": "Contractor",
          "amount": 60000,
          "pct_of_segment": 5.16
        },
        {
          "rank": 4,
          "name": "Fivium Ltd",
          "type": "Contractor",
          "amount": 58235,
          "pct_of_segment": 5.01
        }
      ]
    },
    {
      "segment": "Strategy And Commmunications",
      "total": 664790,
      "transactions": 91,
      "top_recipients": [
        {
          "rank": 1,
          "name": "TPXimpact Limited",
          "type": "Contractor",
          "amount": 225606,
          "pct_of_segment": 33.94
        },
        {
          "rank": 2,
          "name": "CABINET OFFICE HR SHARED SERVICES",
          "type": "Contractor",
          "amount": 180627,
          "pct_of_segment": 27.17
        },
        {
          "rank": 3,
          "name": "CORPORATE TRAVEL MANAGEMENT(NORTH)L",
          "type": "Contractor",
          "amount": 61413,
          "pct_of_segment": 9.24
        },
        {
          "rank": 4,
          "name": "Fivium Ltd",
          "type": "Contractor",
          "amount": 58235,
          "pct_of_segment": 8.76
        },
        {
          "rank": 5,
          "name": "AirWalk Consulting Reply Ltd",
          "type": "Contractor",
          "amount": 42141,
          "pct_of_segment": 6.34
        },
        {
          "rank": 6,
          "name": "GOVERNMENT CAR & DESPATCH AGENCY",
          "type": "Contractor",
          "amount": 28056,
          "pct_of_segment": 4.22
        },
        {
          "rank": 7,
          "name": "Arcturus Security Limited",
          "type": "Contractor",
          "amount": 17160,
          "pct_of_segment": 2.58
        },
        {
          "rank": 8,
          "name": "Howard Kennedy",
          "type": "Contractor",
          "amount": 10543,
          "pct_of_segment": 1.59
        },
        {
          "rank": 9,
          "name": "Juicy Media Ltd",
          "type": "Contractor",
          "amount": 7140,
          "pct_of_segment": 1.07
        },
        {
          "rank": 10,
          "name": "Shutterstock Ireland Limited",
          "type": "Contractor",
          "amount": 6615,
          "pct_of_segment": 1
        },
        {
          "rank": 11,
          "name": "WILLIS NEWS DISTRIBUTION LTD",
          "type": "Contractor",
          "amount": 5592,
          "pct_of_segment": 0.84
        },
        {
          "rank": 12,
          "name": "Employee Expenses",
          "type": "Contractor",
          "amount": 5165,
          "pct_of_segment": 0.78
        },
        {
          "rank": 13,
          "name": "Terry Tew Sound & Light Ltd",
          "type": "Contractor",
          "amount": 4342,
          "pct_of_segment": 0.65
        },
        {
          "rank": 14,
          "name": "CALDER CONFERENCES  LTD",
          "type": "Contractor",
          "amount": 4289,
          "pct_of_segment": 0.65
        },
        {
          "rank": 15,
          "name": "Audio Network Rights Ltd",
          "type": "Contractor",
          "amount": 2400,
          "pct_of_segment": 0.36
        },
        {
          "rank": 16,
          "name": "INFRASTRUCTURE AND PROJECTS AUT",
          "type": "Contractor",
          "amount": 1500,
          "pct_of_segment": 0.23
        },
        {
          "rank": 17,
          "name": "JONES YARRELL LEADENHALL LTD",
          "type": "Contractor",
          "amount": 1152,
          "pct_of_segment": 0.17
        },
        {
          "rank": 18,
          "name": "ERNST & YOUNG LLP",
          "type": "Contractor",
          "amount": 882,
          "pct_of_segment": 0.13
        },
        {
          "rank": 19,
          "name": "WILLIAM LEA COMPANY(TSO)",
          "type": "Contractor",
          "amount": 666,
          "pct_of_segment": 0.1
        },
        {
          "rank": 20,
          "name": "RIBA 1834 LTD",
          "type": "Contractor",
          "amount": 480,
          "pct_of_segment": 0.07
        }
      ]
    },
    {
      "segment": "Not assigned",
      "total": 340195,
      "transactions": 3,
      "top_recipients": [
        {
          "rank": 1,
          "name": "GOVERNMENT LEGAL DEPARTMENT",
          "type": "Contractor",
          "amount": 339588,
          "pct_of_segment": 99.82
        },
        {
          "rank": 2,
          "name": "BANNER BUSINESS SUPPLIES LTD",
          "type": "Contractor",
          "amount": 607,
          "pct_of_segment": 0.18
        }
      ]
    },
    {
      "segment": "Union and Windsor Framework",
      "total": 229571,
      "transactions": 35,
      "top_recipients": [
        {
          "rank": 1,
          "name": "NEATH PORT TALBOT CBC",
          "type": "Contractor",
          "amount": 75000,
          "pct_of_segment": 32.67
        },
        {
          "rank": 2,
          "name": "Verian Group UK Limited",
          "type": "Contractor",
          "amount": 69523,
          "pct_of_segment": 30.28
        },
        {
          "rank": 3,
          "name": "CABINET OFFICE HR SHARED SERVICES",
          "type": "Contractor",
          "amount": 32438,
          "pct_of_segment": 14.13
        },
        {
          "rank": 4,
          "name": "CORPORATE TRAVEL MANAGEMENT(NORTH)L",
          "type": "Contractor",
          "amount": 31146,
          "pct_of_segment": 13.57
        },
        {
          "rank": 5,
          "name": "Live Group Ltd",
          "type": "Contractor",
          "amount": 7746,
          "pct_of_segment": 3.37
        },
        {
          "rank": 6,
          "name": "Total Merchandise Limited",
          "type": "Contractor",
          "amount": 4427,
          "pct_of_segment": 1.93
        },
        {
          "rank": 7,
          "name": "CALDER CONFERENCES  LTD",
          "type": "Contractor",
          "amount": 2922,
          "pct_of_segment": 1.27
        },
        {
          "rank": 8,
          "name": "Warwick Corporate Events Ltd",
          "type": "Contractor",
          "amount": 2502,
          "pct_of_segment": 1.09
        },
        {
          "rank": 9,
          "name": "Official Travel and Subsistence",
          "type": "Contractor",
          "amount": 2180,
          "pct_of_segment": 0.95
        },
        {
          "rank": 10,
          "name": "LOCAL GOVERNMENT ASSOCIATION",
          "type": "Contractor",
          "amount": 805,
          "pct_of_segment": 0.35
        },
        {
          "rank": 11,
          "name": "HM REVENUE & CUSTOMS",
          "type": "Contractor",
          "amount": 323,
          "pct_of_segment": 0.14
        },
        {
          "rank": 12,
          "name": "DCLG GOVERNMENT PROCUREMENT CARD",
          "type": "Contractor",
          "amount": 309,
          "pct_of_segment": 0.13
        },
        {
          "rank": 13,
          "name": "Caffi Bach Y Bocs",
          "type": "Contractor",
          "amount": 250,
          "pct_of_segment": 0.11
        }
      ]
    },
    {
      "segment": "Undefined DGGroup",
      "total": 49977,
      "transactions": 4,
      "top_recipients": [
        {
          "rank": 1,
          "name": "CGI IT UK LIMITED",
          "type": "Contractor",
          "amount": 49977,
          "pct_of_segment": 100
        }
      ]
    },
    {
      "segment": "Stronger Places",
      "total": 4995,
      "transactions": 4,
      "top_recipients": [
        {
          "rank": 1,
          "name": "RAYMOND HILL",
          "type": "Contractor",
          "amount": 4104,
          "pct_of_segment": 82.16
        },
        {
          "rank": 2,
          "name": "CORPORATE TRAVEL MANAGEMENT(NORTH)L",
          "type": "Contractor",
          "amount": 891,
          "pct_of_segment": 17.84
        }
      ]
    },
    {
      "segment": "5106307021",
      "total": 376,
      "transactions": 1,
      "top_recipients": [
        {
          "rank": 1,
          "name": "GOVERNMENT LEGAL DEPARTMENT",
          "type": "Contractor",
          "amount": 376,
          "pct_of_segment": 100
        }
      ]
    }
  ],
  "source": "UK Government Spending Over £25,000, MHCLG, 2024",
  "note": "Segmented by expense area. Only covers transactions over £25,000.",
  "generated": "2026-04-08"
}