{"name": "UK Government Spending 2022-23", "value": 1293452336000, "children": [{"id": "dep", "name": "DEPARTMENT OF HEALTH", "value": 254378018000, "children": [{"id": "nhs_tr", "name": "NHS Trusts", "value": 222286912000, "children": [{"id": "7.a_medi", "name": "7.A Medical services", "value": 116450338000}, {"id": "n/a", "name": "n/a", "value": 105836574000}]}, {"id": "nhs_co", "name": "NHS Commissioning Board (NHS England)", "value": 66813292000, "children": [{"id": "7.a_medi", "name": "7.A Medical services", "value": 51040268000}, {"id": "n/a", "name": "n/a", "value": 15773024000}]}, {"id": "depart", "name": "Department of Health (NHS)", "value": -41914024000, "children": [{"id": "7.c_cent", "name": "7.C Central and other health services", "value": -50843045000}, {"id": "n/a", "name": "n/a", "value": 4316804000}, {"id": "7.a_medi", "name": "7.A Medical services", "value": 3243650000}, {"id": "7.b_medi", "name": "7.B Medical research", "value": 1368567000}]}, {"id": "health", "name": "Health Education England", "value": 3582384000, "children": [{"id": "n/a", "name": "n/a", "value": 1791740000}, {"id": "7.a_medi", "name": "7.A Medical services", "value": 1791500000}, {"id": "7.c_cent", "name": "7.C Central and other health services", "value": -856000}]}, {"id": "health", "name": "Health & Social Care Information Centre (NHS Digital)", "value": 1381415000, "children": [{"id": "7.c_cent", "name": "7.C Central and other health services", "value": 731964000}, {"id": "n/a", "name": "n/a", "value": 649451000}]}, {"id": "nhs_pr", "name": "NHS Property Services", "value": 1183250000, "children": [{"id": "7.c_cent", "name": "7.C Central and other health services", "value": 677352000}, {"id": "n/a", "name": "n/a", "value": 505898000}]}, {"id": "commun", "name": "Community Health Partnership", "value": 625485000, "children": [{"id": "n/a", "name": "n/a", "value": 317400000}, {"id": "7.c_cent", "name": "7.C Central and other health services", "value": 308085000}]}, {"id": "genomi", "name": "Genomics England Limited", "value": 200952000, "children": [{"id": "n/a", "name": "n/a", "value": 106817000}, {"id": "7.c_cent", "name": "7.C Central and other health services", "value": 94135000}]}, {"id": "care_q", "name": "Care Quality Commission", "value": 150073000, "children": [{"id": "7.c_cent", "name": "7.C Central and other health services", "value": 86596000}, {"id": "n/a", "name": "n/a", "value": 63477000}]}, {"id": "supply", "name": "Supply Chain Coordination Limited", "value": -135188000, "children": [{"id": "7.c_cent", "name": "7.C Central and other health services", "value": -67594000}, {"id": "n/a", "name": "n/a", "value": -67594000}]}, {"id": "nation", "name": "National Institute for Health and Care Excellence", "value": 120838000, "children": [{"id": "7.c_cent", "name": "7.C Central and other health services", "value": 61694000}, {"id": "n/a", "name": "n/a", "value": 59144000}]}, {"id": "health", "name": "Health Research Authority", "value": 39536000, "children": [{"id": "7.c_cent", "name": "7.C Central and other health services", "value": 21091000}, {"id": "n/a", "name": "n/a", "value": 18445000}]}, {"id": "office", "name": "Office of the Independent Regulator for NHS Foundation Trusts (NHS Improvement)", "value": 16118000, "children": [{"id": "7.c_cent", "name": "7.C Central and other health services", "value": 9118000}, {"id": "n/a", "name": "n/a", "value": 7000000}]}, {"id": "nursin", "name": "Nursing and Midwifery Council", "value": 7325000, "children": [{"id": "7.c_cent", "name": "7.C Central and other health services", "value": 7126000}, {"id": "n/a", "name": "n/a", "value": 199000}]}, {"id": "profes", "name": "Professional Standards Authority for Health and Social Care", "value": 5885000, "children": [{"id": "7.c_cent", "name": "7.C Central and other health services", "value": 3102000}, {"id": "n/a", "name": "n/a", "value": 2783000}]}, {"id": "human_", "name": "Human Tissue Authority", "value": 5355000, "children": [{"id": "n/a", "name": "n/a", "value": 2822000}, {"id": "7.c_cent", "name": "7.C Central and other health services", "value": 2533000}]}, {"id": "human_", "name": "Human Fertilisation and Embryology Authority", "value": 5250000, "children": [{"id": "7.c_cent", "name": "7.C Central and other health services", "value": 2782000}, {"id": "n/a", "name": "n/a", "value": 2468000}]}, {"id": "health", "name": "Health and Care Professions Council", "value": 3160000, "children": [{"id": "7.c_cent", "name": "7.C Central and other health services", "value": 2623000}, {"id": "n/a", "name": "n/a", "value": 537000}]}]}, {"id": "dep", "name": "DEPARTMENT FOR WORK AND PENSIONS", "value": 245050019000, "children": [{"id": "depart", "name": "Department for Work and Pensions", "value": 244147369000, "children": [{"id": "10.2_old", "name": "10.2 Old age; of which: pensions", "value": 118544591000}, {"id": "10.7_soc", "name": "10.7 Social exclusion n.e.c.; of which: family benefits, income support and tax credits", "value": 45471499000}, {"id": "10.1_sic", "name": "10.1 Sickness and disability; of which: incapacity, disability and injury benefits", "value": 44766538000}, {"id": "10.6_hou", "name": "10.6 Housing", "value": 15087361000}, {"id": "10.9_soc", "name": "10.9 Social protection n.e.c.", "value": 9958464000}, {"id": "n/a", "name": "n/a", "value": 5872317000}, {"id": "4.1_gene", "name": "4.1 General economic, commercial and labour affairs", "value": 3043911000}, {"id": "10.4_fam", "name": "10.4 Family and children; of which: family benefits, income support and tax credits", "value": 512814000}, {"id": "10.3_sur", "name": "10.3 Survivors", "value": 414353000}, {"id": "10.5_une", "name": "10.5 Unemployment; of which: other unemployment benefits", "value": 345340000}, {"id": "1.1_exec", "name": "1.1 Executive and legislative organs, financial and fiscal affairs, external affairs", "value": 127089000}, {"id": "4.3_fuel", "name": "4.3 Fuel and energy", "value": 3091000}, {"id": "4.9_econ", "name": "4.9 Economic affairs n.e.c.", "value": 1000}]}, {"id": "health", "name": "Health and Safety Executive", "value": 344595000, "children": [{"id": "n/a", "name": "n/a", "value": 173982000}, {"id": "4.1_gene", "name": "4.1 General economic, commercial and labour affairs", "value": 172348000}, {"id": "4.8_r&d_", "name": "4.8 R&D economic affairs", "value": -1735000}]}, {"id": "single", "name": "Single Financial Guidance Body", "value": 330310000, "children": [{"id": "10.9_soc", "name": "10.9 Social protection n.e.c.", "value": 167641000}, {"id": "n/a", "name": "n/a", "value": 162669000}]}, {"id": "the_pe", "name": "The Pensions Regulator", "value": 206162000, "children": [{"id": "10.9_soc", "name": "10.9 Social protection n.e.c.", "value": 104787000}, {"id": "n/a", "name": "n/a", "value": 101375000}]}, {"id": "the_pe", "name": "The Pensions Ombudsman", "value": 21583000, "children": [{"id": "10.9_soc", "name": "10.9 Social protection n.e.c.", "value": 10956000}, {"id": "n/a", "name": "n/a", "value": 10627000}]}]}, {"id": "loc", "name": "LOCAL GOVERNMENT ENGLAND", "value": 149860974000, "children": [{"id": "englan", "name": "England Local Authorities", "value": 145188057000, "children": [{"id": "9.1_of_w", "name": "9.1 of which: primary education", "value": 23592094000}, {"id": "3.1_of_w", "name": "3.1 of which: other police services", "value": 15260146000}, {"id": "10.6_hou", "name": "10.6 Housing", "value": 14333487000}, {"id": "10.4_fam", "name": "10.4 Family and children; of which: personal social services", "value": 12602634000}, {"id": "10.1_sic", "name": "10.1 Sickness and disability; of which: personal social services", "value": 10991512000}, {"id": "10.2_old", "name": "10.2 Old age; of which: personal social services", "value": 10281896000}, {"id": "9.2_seco", "name": "9.2 Secondary education", "value": 6685834000}, {"id": "5.1_wast", "name": "5.1 Waste management", "value": 5673455000}, {"id": "9.6_subs", "name": "9.6 Subsidiary services to education", "value": 4738226000}, {"id": "4.5_of_w", "name": "4.5 of which: local roads", "value": 4565180000}, {"id": "7.a_medi", "name": "7.A Medical services", "value": 3889308000}, {"id": "9.1_of_w", "name": "9.1 of which: under fives", "value": 3570898000}, {"id": "4.5_of_w", "name": "4.5 of which: local public transport", "value": 3197496000}, {"id": "6.2_comm", "name": "6.2 Community development", "value": 2718438000}, {"id": "3.2_fire", "name": "3.2 Fire-protection services", "value": 2608076000}, {"id": "4.5_of_w", "name": "4.5 of which: railway", "value": 2347431000}, {"id": "1.6_gene", "name": "1.6 General public services n.e.c.", "value": 2276741000}, {"id": "6.1_of_w", "name": "6.1 of which: local authority housing", "value": 2139713000}, {"id": "8.1_recr", "name": "8.1 Recreational and sporting services", "value": 2124867000}, {"id": "1.1_exec", "name": "1.1 Executive and legislative organs, financial and fiscal affairs, external affairs", "value": 1834100000}, {"id": "10.7_soc", "name": "10.7 Social exclusion n.e.c.; of which: personal social services", "value": 1633369000}, {"id": "8.2_cult", "name": "8.2 Cultural services", "value": 1607270000}, {"id": "1.3_gene", "name": "1.3 General services", "value": 1159760000}, {"id": "4.1_gene", "name": "4.1 General economic, commercial and labour affairs", "value": 1026018000}, {"id": "6.4_stre", "name": "6.4 Street lighting", "value": 845875000}, {"id": "9.3_post", "name": "9.3 Post-secondary non-tertiary education", "value": 730476000}, {"id": "4.4_mini", "name": "4.4 Mining, manufacturing and construction", "value": 629404000}, {"id": "5.6_envi", "name": "5.6 Environment protection n.e.c.", "value": 607766000}, {"id": "10.2_old", "name": "10.2 Old age; of which: pensions", "value": 531742000}, {"id": "4.2_of_w", "name": "4.2 of which: other agriculture, food and fisheries policy", "value": 359643000}, {"id": "10.9_soc", "name": "10.9 Social protection n.e.c.", "value": 244843000}, {"id": "3.3_law_", "name": "3.3 Law courts", "value": 141539000}, {"id": "4.5_of_w", "name": "4.5 of which: other transport", "value": 115353000}, {"id": "4.7_othe", "name": "4.7 Other industries", "value": 79811000}, {"id": "2.2_civi", "name": "2.2 Civil defence", "value": 79796000}, {"id": "8.4_reli", "name": "8.4 Religious and other community services", "value": -36140000}]}, {"id": "englan", "name": "England Housing Revenue Account", "value": 4672917000}]}, {"id": "hm", "name": "HM TREASURY", "value": 130608429000, "children": [{"id": "hm_tre", "name": "HM Treasury", "value": 130064611000, "children": [{"id": "4.1_gene", "name": "4.1 General economic, commercial and labour affairs", "value": 140257565000}, {"id": "n/a", "name": "n/a", "value": -5229749000}, {"id": "1.1_exec", "name": "1.1 Executive and legislative organs, financial and fiscal affairs, external affairs", "value": -4967442000}, {"id": "10.2_old", "name": "10.2 Old age; of which: pensions", "value": 4237000}]}, {"id": "nation", "name": "National Wealth Fund Limited", "value": 263505000}, {"id": "royal_", "name": "Royal Household (HMT087.GROUP)", "value": 187791000, "children": [{"id": "1.1_exec", "name": "1.1 Executive and legislative organs, financial and fiscal affairs, external affairs", "value": 103191000}, {"id": "n/a", "name": "n/a", "value": 84600000}]}, {"id": "office", "name": "Office for Budget Responsibility", "value": 67825000, "children": [{"id": "n/a", "name": "n/a", "value": 63408000}, {"id": "1.1_exec", "name": "1.1 Executive and legislative organs, financial and fiscal affairs, external affairs", "value": 4417000}]}, {"id": "reclai", "name": "Reclaim Fund Ltd", "value": -49741000}, {"id": "pool_r", "name": "Pool Reinsurance Company Limited", "value": 35072000, "children": [{"id": "4.1_gene", "name": "4.1 General economic, commercial and labour affairs", "value": 21015000}, {"id": "1.1_exec", "name": "1.1 Executive and legislative organs, financial and fiscal affairs, external affairs", "value": 14057000}]}, {"id": "united", "name": "United Kingdom Government Investments Limited", "value": 34328000, "children": [{"id": "4.1_gene", "name": "4.1 General economic, commercial and labour affairs", "value": 17178000}, {"id": "1.1_exec", "name": "1.1 Executive and legislative organs, financial and fiscal affairs, external affairs", "value": 17150000}]}, {"id": "uk_ass", "name": "UK Asset Resolution (net)", "value": 5038000}]}, {"id": "dep", "name": "DEPARTMENT FOR EDUCATION", "value": 73709913000, "children": [{"id": "depart", "name": "Department for Education", "value": 82033376000, "children": [{"id": "9.5_educ", "name": "9.5 Education not definable by level", "value": 43822609000}, {"id": "9.8_educ", "name": "9.8 Education n.e.c.", "value": 25129974000}, {"id": "9.1_of_w", "name": "9.1 of which: under fives", "value": 3987014000}, {"id": "9.2_seco", "name": "9.2 Secondary education", "value": 3942774000}, {"id": "9.1_of_w", "name": "9.1 of which: primary education", "value": 2483353000}, {"id": "9.4_tert", "name": "9.4 Tertiary education", "value": 1767712000}, {"id": "10.4_fam", "name": "10.4 Family and children; of which: personal social services", "value": 577723000}, {"id": "not_know", "name": "Not known", "value": 174557000}, {"id": "9.6_subs", "name": "9.6 Subsidiary services to education", "value": 71875000}, {"id": "10.9_soc", "name": "10.9 Social protection n.e.c.", "value": 47560000}, {"id": "10.4_fam", "name": "10.4 Family and children; of which: family benefits, income support and tax credits", "value": 17559000}, {"id": "10.2_old", "name": "10.2 Old age; of which: pensions", "value": 11026000}, {"id": "n/a", "name": "n/a", "value": -360000}]}, {"id": "dfe_gr", "name": "DfE Grants to Academies Offset", "value": -30914885000, "children": [{"id": "9.5_educ", "name": "9.5 Education not definable by level", "value": -26019302000}, {"id": "9.1_of_w", "name": "9.1 of which: primary education", "value": -2483353000}, {"id": "9.2_seco", "name": "9.2 Secondary education", "value": -2029305000}, {"id": "9.1_of_w", "name": "9.1 of which: under fives", "value": -226694000}, {"id": "not_know", "name": "Not known", "value": -119556000}, {"id": "9.8_educ", "name": "9.8 Education n.e.c.", "value": -36675000}]}, {"id": "academ", "name": "Academies", "value": 18996264000}, {"id": "office", "name": "Office for Students", "value": 2913842000}, {"id": "studen", "name": "Student Loans Company", "value": 612179000, "children": [{"id": "9.4_tert", "name": "9.4 Tertiary education", "value": 323040000}, {"id": "9.5_educ", "name": "9.5 Education not definable by level", "value": 289139000}]}, {"id": "instit", "name": "Institute for Apprenticeship", "value": 58747000, "children": [{"id": "9.5_educ", "name": "9.5 Education not definable by level", "value": 29535000}, {"id": "n/a", "name": "n/a", "value": 29212000}]}, {"id": "aggreg", "name": "Aggregator Vehicle PLC", "value": -41429000}, {"id": "social", "name": "Social Work England", "value": 32309000}, {"id": "locate", "name": "LocatED PLC", "value": 15638000, "children": [{"id": "n/a", "name": "n/a", "value": 7831000}, {"id": "9.8_educ", "name": "9.8 Education n.e.c.", "value": 7807000}]}, {"id": "constr", "name": "Construction Industry Training Board", "value": -10485000}, {"id": "oak_na", "name": "Oak National Academy Limited", "value": 6615000, "children": [{"id": "9.5_educ", "name": "9.5 Education not definable by level", "value": 3848000}, {"id": "n/a", "name": "n/a", "value": 2767000}]}, {"id": "childr", "name": "Children's Commissioner", "value": 5694000, "children": [{"id": "10.9_soc", "name": "10.9 Social protection n.e.c.", "value": 2849000}, {"id": "n/a", "name": "n/a", "value": 2845000}]}, {"id": "engine", "name": "Engineering Construction Industry Training Board", "value": 2048000}]}, {"id": "dep", "name": "DEPARTMENT FOR ENERGY SECURITY AND NET ZERO", "value": -72996350000, "children": [{"id": "nuclea", "name": "Nuclear Decommissioning Authority", "value": -103486041000, "children": [{"id": "5.1_wast", "name": "5.1 Waste management", "value": -106633265000}, {"id": "n/a", "name": "n/a", "value": 3147224000}]}, {"id": "depart", "name": "Department for Energy Security and Net Zero", "value": 45941269000, "children": [{"id": "4.3_fuel", "name": "4.3 Fuel and energy", "value": 45969580000}, {"id": "5.1_wast", "name": "5.1 Waste management", "value": -1099144000}, {"id": "5.3_poll", "name": "5.3 Pollution abatement", "value": 783094000}, {"id": "4.9_econ", "name": "4.9 Economic affairs n.e.c.", "value": 314596000}, {"id": "5.6_envi", "name": "5.6 Environment protection n.e.c.", "value": 245657000}, {"id": "10.1_sic", "name": "10.1 Sickness and disability; of which: incapacity, disability and injury benefits", "value": -160946000}, {"id": "n/a", "name": "n/a", "value": -142400000}, {"id": "1.1_exec", "name": "1.1 Executive and legislative organs, financial and fiscal affairs, external affairs", "value": 38491000}, {"id": "4.4_mini", "name": "4.4 Mining, manufacturing and construction", "value": -14051000}, {"id": "5.5_r&d_", "name": "5.5 R&D environment protection", "value": 6429000}, {"id": "4.1_gene", "name": "4.1 General economic, commercial and labour affairs", "value": -37000}]}, {"id": "low_ca", "name": "Low Carbon Contracts Company", "value": -13501000000}, {"id": "coal_a", "name": "Coal Authority", "value": -3269496000, "children": [{"id": "5.4_prot", "name": "5.4 Protection of biodiversity and landscape", "value": -3327536000}, {"id": "n/a", "name": "n/a", "value": 58040000}]}, {"id": "sizewe", "name": "Sizewell C Limited", "value": 841230000}, {"id": "united", "name": "United Kingdom Atomic Energy Authority", "value": 515993000, "children": [{"id": "5.1_wast", "name": "5.1 Waste management", "value": 267421000}, {"id": "n/a", "name": "n/a", "value": 248572000}]}, {"id": "enrich", "name": "Enrichment Holdings Ltd", "value": -87513000}, {"id": "salix", "name": "Salix", "value": 21198000, "children": [{"id": "5.3_poll", "name": "5.3 Pollution abatement", "value": 11930000}, {"id": "n/a", "name": "n/a", "value": 9268000}]}, {"id": "commit", "name": "Committee on Climate Change", "value": 12712000, "children": [{"id": "5.3_poll", "name": "5.3 Pollution abatement", "value": 6356000}, {"id": "n/a", "name": "n/a", "value": 6356000}]}, {"id": "oil_&_", "name": "Oil & Gas Authority", "value": 11909000, "children": [{"id": "4.3_fuel", "name": "4.3 Fuel and energy", "value": 9959000}, {"id": "n/a", "name": "n/a", "value": 1950000}]}, {"id": "civil_", "name": "Civil Nuclear Police Authority and Constabulary", "value": 3348000, "children": [{"id": "n/a", "name": "n/a", "value": 4386000}, {"id": "3.1_of_w", "name": "3.1 of which: other police services", "value": -1038000}]}, {"id": "uk_gre", "name": "UK Green Infrastructure Platform Entity", "value": 41000}, {"id": "electr", "name": "Electricity Settlements Company", "value": 0}]}, {"id": "dep", "name": "DEPARTMENT FOR TRANSPORT", "value": 60011211000, "children": [{"id": "networ", "name": "Network Rail", "value": 25799674000}, {"id": "high_s", "name": "High Speed 2", "value": 13832299000, "children": [{"id": "4.5_of_w", "name": "4.5 of which: railway", "value": 6960910000}, {"id": "n/a", "name": "n/a", "value": 6871389000}]}, {"id": "nation", "name": "National Highways", "value": 10441338000}, {"id": "depart", "name": "Department for Transport", "value": 9701999000, "children": [{"id": "4.5_of_w", "name": "4.5 of which: railway", "value": 4964800000}, {"id": "4.5_of_w", "name": "4.5 of which: local public transport", "value": 2181444000}, {"id": "4.5_of_w", "name": "4.5 of which: other transport", "value": 1482530000}, {"id": "4.5_of_w", "name": "4.5 of which: local roads", "value": 1139074000}, {"id": "n/a", "name": "n/a", "value": -239914000}, {"id": "4.5_of_w", "name": "4.5 of which: national roads", "value": 164551000}, {"id": "10.2_old", "name": "10.2 Old age; of which: pensions", "value": -58755000}, {"id": "4.8_r&d_", "name": "4.8 R&D economic affairs", "value": 42920000}, {"id": "4.9_econ", "name": "4.9 Economic affairs n.e.c.", "value": 24805000}, {"id": "5.3_poll", "name": "5.3 Pollution abatement", "value": 1304000}, {"id": "1.3_gene", "name": "1.3 General services", "value": -748000}, {"id": "5.5_r&d_", "name": "5.5 R&D environment protection", "value": -12000}]}, {"id": "britis", "name": "British Transport Police Authority", "value": 135082000, "children": [{"id": "3.1_of_w", "name": "3.1 of which: other police services", "value": 133740000}, {"id": "n/a", "name": "n/a", "value": 1342000}]}, {"id": "east_w", "name": "East West Rail", "value": 134801000, "children": [{"id": "n/a", "name": "n/a", "value": 69000000}, {"id": "4.5_of_w", "name": "4.5 of which: railway", "value": 65801000}]}, {"id": "air_tr", "name": "Air Travel Trust", "value": -54960000}, {"id": "trinit", "name": "Trinity House Lighthouse Service", "value": 13675000}, {"id": "transp", "name": "Transport Focus", "value": 13165000, "children": [{"id": "n/a", "name": "n/a", "value": 6679000}, {"id": "4.5_of_w", "name": "4.5 of which: railway", "value": 6486000}]}, {"id": "train_", "name": "Train Fleet", "value": -7928000}, {"id": "northe", "name": "Northern Lighthouse Board", "value": 1761000}, {"id": "commis", "name": "Commissioners of Irish Lights", "value": 305000}, {"id": "london", "name": "London and Continental Railways", "value": 0}]}, {"id": "sco", "name": "SCOTLAND OFFICE AND OFFICE OF THE ADVOCATE GENERAL", "value": 47765152000, "children": [{"id": "scotla", "name": "Scotland Office and Office of the Advocate General", "value": 47765152000, "children": [{"id": "n/a", "name": "n/a", "value": 32359971000}, {"id": "not_know", "name": "Not known", "value": 15392555000}, {"id": "1.1_exec", "name": "1.1 Executive and legislative organs, financial and fiscal affairs, external affairs", "value": 12626000}]}]}, {"id": "min", "name": "MINISTRY OF DEFENCE", "value": 43719133000, "children": [{"id": "minist", "name": "Ministry of Defence", "value": 43261800000, "children": [{"id": "2.1_mili", "name": "2.1 Military defence", "value": 40327120000}, {"id": "2.4_r&d_", "name": "2.4 R&D defence", "value": 2252655000}, {"id": "10.2_old", "name": "10.2 Old age; of which: pensions", "value": 606730000}, {"id": "2.3_fore", "name": "2.3 Foreign military aid", "value": 75295000}]}, {"id": "territ", "name": "Territorial, Auxiliary and Volunteer Reserve Associations established under s 110 of the Reserve Act", "value": 233118000, "children": [{"id": "2.5_defe", "name": "2.5 Defence n.e.c.", "value": 126170000}, {"id": "n/a", "name": "n/a", "value": 106948000}]}, {"id": "common", "name": "Commonwealth War Graves Commission", "value": 105426000, "children": [{"id": "2.5_defe", "name": "2.5 Defence n.e.c.", "value": 52713000}, {"id": "n/a", "name": "n/a", "value": 52713000}]}, {"id": "armed_", "name": "Armed Forces Covenant Fund Trustee Ltd", "value": 29597000, "children": [{"id": "2.5_defe", "name": "2.5 Defence n.e.c.", "value": 19183000}, {"id": "n/a", "name": "n/a", "value": 10414000}]}, {"id": "royal_", "name": "Royal Hospital, Chelsea", "value": 27336000, "children": [{"id": "2.5_defe", "name": "2.5 Defence n.e.c.", "value": 13668000}, {"id": "n/a", "name": "n/a", "value": 13668000}]}, {"id": "royal_", "name": "Royal Air Force Museum", "value": 20592000, "children": [{"id": "8.2_cult", "name": "8.2 Cultural services", "value": 10296000}, {"id": "n/a", "name": "n/a", "value": 10296000}]}, {"id": "nation", "name": "National Army Museum", "value": 14362000, "children": [{"id": "8.2_cult", "name": "8.2 Cultural services", "value": 7181000}, {"id": "n/a", "name": "n/a", "value": 7181000}]}, {"id": "nation", "name": "National Museum of the Royal Navy", "value": 13518000, "children": [{"id": "8.2_cult", "name": "8.2 Cultural services", "value": 6759000}, {"id": "n/a", "name": "n/a", "value": 6759000}]}, {"id": "single", "name": "Single Source Regulations Office", "value": 13382000, "children": [{"id": "2.5_defe", "name": "2.5 Defence n.e.c.", "value": 6691000}, {"id": "n/a", "name": "n/a", "value": 6691000}]}, {"id": "intern", "name": "International Military Services Limited", "value": 2000, "children": [{"id": "2.5_defe", "name": "2.5 Defence n.e.c.", "value": 1000}, {"id": "n/a", "name": "n/a", "value": 1000}]}]}, {"id": "hm", "name": "HM REVENUE AND CUSTOMS", "value": 41014822000, "children": [{"id": "hm_rev", "name": "HM Revenue & Customs", "value": 41014822000, "children": [{"id": "4.1_gene", "name": "4.1 General economic, commercial and labour affairs", "value": 13285688000}, {"id": "10.4_fam", "name": "10.4 Family and children; of which: family benefits, income support and tax credits", "value": 12616162000}, {"id": "10.7_soc", "name": "10.7 Social exclusion n.e.c.; of which: family benefits, income support and tax credits", "value": 9567840000}, {"id": "1.1_exec", "name": "1.1 Executive and legislative organs, financial and fiscal affairs, external affairs", "value": 5245961000}, {"id": "6.6_hous", "name": "6.6 Housing and community amenities n.e.c.", "value": 182089000}, {"id": "10.2_old", "name": "10.2 Old age; of which: pensions", "value": 80000000}, {"id": "1.6_gene", "name": "1.6 General public services n.e.c.", "value": -72030000}, {"id": "n/a", "name": "n/a", "value": 63799000}, {"id": "5.6_envi", "name": "5.6 Environment protection n.e.c.", "value": 45311000}, {"id": "10.6_hou", "name": "10.6 Housing", "value": 2000}]}]}, {"id": "sco", "name": "SCOTTISH GOVERNMENT", "value": 39700983000, "children": [{"id": "scotti", "name": "Scottish Government", "value": 39700983000, "children": [{"id": "n/a", "name": "n/a", "value": -18807158000}, {"id": "7.a_medi", "name": "7.A Medical services", "value": 16248700000}, {"id": "1.6_gene", "name": "1.6 General public services n.e.c.", "value": 11785361000}, {"id": "10.2_old", "name": "10.2 Old age; of which: pensions", "value": 7140900000}, {"id": "10.1_sic", "name": "10.1 Sickness and disability; of which: incapacity, disability and injury benefits", "value": 3452528000}, {"id": "3.1_of_w", "name": "3.1 of which: other police services", "value": 2104756000}, {"id": "4.5_of_w", "name": "4.5 of which: railway", "value": 2013540000}, {"id": "9.4_tert", "name": "9.4 Tertiary education", "value": 1699516000}, {"id": "4.1_gene", "name": "4.1 General economic, commercial and labour affairs", "value": 1394986000}, {"id": "10.9_soc", "name": "10.9 Social protection n.e.c.", "value": 1021917000}, {"id": "4.5_of_w", "name": "4.5 of which: national roads", "value": 907914000}, {"id": "1.1_exec", "name": "1.1 Executive and legislative organs, financial and fiscal affairs, external affairs", "value": 906951000}, {"id": "9.2_seco", "name": "9.2 Secondary education", "value": 748100000}, {"id": "6.1_of_w", "name": "6.1 of which: other social housing", "value": 735806000}, {"id": "6.3_wate", "name": "6.3 Water supply", "value": 642494000}, {"id": "3.3_law_", "name": "3.3 Law courts", "value": 637321000}, {"id": "7.c_cent", "name": "7.C Central and other health services", "value": 618720000}, {"id": "4.5_of_w", "name": "4.5 of which: other transport", "value": 539497000}, {"id": "9.1_of_w", "name": "9.1 of which: under fives", "value": 531111000}, {"id": "3.2_fire", "name": "3.2 Fire-protection services", "value": 512835000}, {"id": "3.4_pris", "name": "3.4 Prisons", "value": 497710000}, {"id": "4.2_of_w", "name": "4.2 of which: market support under CAP", "value": 473565000}, {"id": "4.5_of_w", "name": "4.5 of which: local public transport", "value": 460816000}, {"id": "9.6_subs", "name": "9.6 Subsidiary services to education", "value": 459557000}, {"id": "10.7_soc", "name": "10.7 Social exclusion n.e.c.; of which: family benefits, income support and tax credits", "value": 429638000}, {"id": "9.8_educ", "name": "9.8 Education n.e.c.", "value": 419819000}, {"id": "7.b_medi", "name": "7.B Medical research", "value": 373489000}, {"id": "5.6_envi", "name": "5.6 Environment protection n.e.c.", "value": 273759000}, {"id": "8.2_cult", "name": "8.2 Cultural services", "value": 269452000}, {"id": "4.2_of_w", "name": "4.2 of which: other agriculture, food and fisheries policy", "value": 246610000}, {"id": "5.4_prot", "name": "5.4 Protection of biodiversity and landscape", "value": 144512000}, {"id": "4.6_comm", "name": "4.6 Communication", "value": 127623000}, {"id": "4.2_of_w", "name": "4.2 of which: forestry", "value": 118365000}, {"id": "4.9_econ", "name": "4.9 Economic affairs n.e.c.", "value": 112837000}, {"id": "3.6_publ", "name": "3.6 Public order and safety n.e.c.", "value": 109038000}, {"id": "4.7_othe", "name": "4.7 Other industries", "value": 66578000}, {"id": "8.1_recr", "name": "8.1 Recreational and sporting services", "value": 59524000}, {"id": "10.4_fam", "name": "10.4 Family and children; of which: family benefits, income support and tax credits", "value": 47549000}, {"id": "10.4_fam", "name": "10.4 Family and children; of which: personal social services", "value": 33442000}, {"id": "5.1_wast", "name": "5.1 Waste management", "value": 32124000}, {"id": "1.3_gene", "name": "1.3 General services", "value": 26975000}, {"id": "6.2_comm", "name": "6.2 Community development", "value": 26132000}, {"id": "1.5_r&d_", "name": "1.5 R&D general public services", "value": 9885000}, {"id": "10.3_sur", "name": "10.3 Survivors", "value": 9793000}, {"id": "4.5_of_w", "name": "4.5 of which: local roads", "value": 8812000}, {"id": "10.5_une", "name": "10.5 Unemployment; of which: other unemployment benefits", "value": 8453000}, {"id": "8.3_broa", "name": "8.3 Broadcasting and publishing services", "value": 7154000}, {"id": "5.3_poll", "name": "5.3 Pollution abatement", "value": 2922000}, {"id": "6.5_r&d_", "name": "6.5 R&D housing and community amenities", "value": 2869000}, {"id": "6.6_hous", "name": "6.6 Housing and community amenities n.e.c.", "value": 2831000}, {"id": "4.8_r&d_", "name": "4.8 R&D economic affairs", "value": 2517000}, {"id": "1.2_fore", "name": "1.2 Foreign economic aid", "value": 1000000}, {"id": "9.7_r&d_", "name": "9.7 R&D education", "value": -162000}]}]}, {"id": "min", "name": "MINISTRY OF HOUSING, COMMUNITIES AND LOCAL GOVERNMENT", "value": 32206063000, "children": [{"id": "mhclg_", "name": "MHCLG Local Government", "value": 22873003000, "children": [{"id": "not_know", "name": "Not known", "value": 13388932000}, {"id": "n/a", "name": "n/a", "value": 9394315000}, {"id": "4.1_gene", "name": "4.1 General economic, commercial and labour affairs", "value": 87473000}, {"id": "6.2_comm", "name": "6.2 Community development", "value": 2283000}]}, {"id": "mhclg_", "name": "MHCLG Communities", "value": 6415221000, "children": [{"id": "6.2_comm", "name": "6.2 Community development", "value": 2964236000}, {"id": "6.6_hous", "name": "6.6 Housing and community amenities n.e.c.", "value": 870124000}, {"id": "4.1_gene", "name": "4.1 General economic, commercial and labour affairs", "value": 647977000}, {"id": "6.1_of_w", "name": "6.1 of which: local authority housing", "value": 456714000}, {"id": "n/a", "name": "n/a", "value": 449328000}, {"id": "1.3_gene", "name": "1.3 General services", "value": 385482000}, {"id": "1.1_exec", "name": "1.1 Executive and legislative organs, financial and fiscal affairs, external affairs", "value": 278605000}, {"id": "10.6_hou", "name": "10.6 Housing", "value": 157233000}, {"id": "6.1_of_w", "name": "6.1 of which: other social housing", "value": 150630000}, {"id": "1.6_gene", "name": "1.6 General public services n.e.c.", "value": 41192000}, {"id": "1.5_r&d_", "name": "1.5 R&D general public services", "value": 9797000}, {"id": "3.2_fire", "name": "3.2 Fire-protection services", "value": -6980000}, {"id": "10.9_soc", "name": "10.9 Social protection n.e.c.", "value": 3780000}, {"id": "8.2_cult", "name": "8.2 Cultural services", "value": 3199000}, {"id": "not_know", "name": "Not known", "value": 2714000}, {"id": "4.9_econ", "name": "4.9 Economic affairs n.e.c.", "value": 1280000}, {"id": "1.2_fore", "name": "1.2 Foreign economic aid", "value": -1211000}, {"id": "10.7_soc", "name": "10.7 Social exclusion n.e.c.; of which: personal social services", "value": 1010000}, {"id": "4.8_r&d_", "name": "4.8 R&D economic affairs", "value": 111000}]}, {"id": "homes_", "name": "Homes England", "value": 2790567000, "children": [{"id": "4.1_gene", "name": "4.1 General economic, commercial and labour affairs", "value": 2236988000}, {"id": "6.1_of_w", "name": "6.1 of which: other social housing", "value": 1382778000}, {"id": "n/a", "name": "n/a", "value": -682690000}, {"id": "not_know", "name": "Not known", "value": -438578000}, {"id": "6.1_of_w", "name": "6.1 of which: local authority housing", "value": 285583000}, {"id": "6.2_comm", "name": "6.2 Community development", "value": 127934000}, {"id": "6.6_hous", "name": "6.6 Housing and community amenities n.e.c.", "value": -121448000}]}, {"id": "the_pl", "name": "The Planning Inspectorate", "value": 61374000}, {"id": "commis", "name": "Commission for Local Administration CLG Main", "value": 30082000, "children": [{"id": "not_know", "name": "Not known", "value": 16798000}, {"id": "1.1_exec", "name": "1.1 Executive and legislative organs, financial and fiscal affairs, external affairs", "value": 13284000}]}, {"id": "regula", "name": "Regulator of Social Housing", "value": 20245000, "children": [{"id": "6.1_of_w", "name": "6.1 of which: other social housing", "value": 11118000}, {"id": "n/a", "name": "n/a", "value": 9127000}]}, {"id": "valuat", "name": "Valuation Tribunal Service CLG Main", "value": 11023000, "children": [{"id": "1.1_exec", "name": "1.1 Executive and legislative organs, financial and fiscal affairs, external affairs", "value": 5972000}, {"id": "not_know", "name": "Not known", "value": 5051000}]}, {"id": "leaseh", "name": "Leasehold Advisory Service", "value": 2684000, "children": [{"id": "4.1_gene", "name": "4.1 General economic, commercial and labour affairs", "value": 1441000}, {"id": "n/a", "name": "n/a", "value": 1243000}]}, {"id": "the_ho", "name": "The Housing Ombudsman", "value": 1864000}]}, {"id": "nor", "name": "NORTHERN IRELAND EXECUTIVE", "value": 29200984000, "children": [{"id": "northe", "name": "Northern Ireland Executive", "value": 28888118000, "children": [{"id": "10.2_old", "name": "10.2 Old age; of which: pensions", "value": 7299114000}, {"id": "7.a_medi", "name": "7.A Medical services", "value": 5709115000}, {"id": "10.1_sic", "name": "10.1 Sickness and disability; of which: incapacity, disability and injury benefits", "value": 2990160000}, {"id": "9.8_educ", "name": "9.8 Education n.e.c.", "value": 2074278000}, {"id": "3.1_of_w", "name": "3.1 of which: other police services", "value": 944199000}, {"id": "9.2_seco", "name": "9.2 Secondary education", "value": 784056000}, {"id": "10.4_fam", "name": "10.4 Family and children; of which: family benefits, income support and tax credits", "value": 751030000}, {"id": "10.2_old", "name": "10.2 Old age; of which: personal social services", "value": 722337000}, {"id": "4.2_of_w", "name": "4.2 of which: other agriculture, food and fisheries policy", "value": 616299000}, {"id": "6.3_wate", "name": "6.3 Water supply", "value": 570420000}, {"id": "7.c_cent", "name": "7.C Central and other health services", "value": 557036000}, {"id": "10.1_sic", "name": "10.1 Sickness and disability; of which: personal social services", "value": 531022000}, {"id": "4.5_of_w", "name": "4.5 of which: local roads", "value": 507239000}, {"id": "9.6_subs", "name": "9.6 Subsidiary services to education", "value": 428240000}, {"id": "10.5_une", "name": "10.5 Unemployment; of which: other unemployment benefits", "value": 421660000}, {"id": "10.6_hou", "name": "10.6 Housing", "value": 413778000}, {"id": "6.1_of_w", "name": "6.1 of which: other social housing", "value": 384353000}, {"id": "10.4_fam", "name": "10.4 Family and children; of which: personal social services", "value": 279844000}, {"id": "1.1_exec", "name": "1.1 Executive and legislative organs, financial and fiscal affairs, external affairs", "value": 279458000}, {"id": "3.3_law_", "name": "3.3 Law courts", "value": 270048000}, {"id": "1.3_gene", "name": "1.3 General services", "value": 246878000}, {"id": "4.5_of_w", "name": "4.5 of which: railway", "value": 225386000}, {"id": "9.4_tert", "name": "9.4 Tertiary education", "value": 218055000}, {"id": "4.1_gene", "name": "4.1 General economic, commercial and labour affairs", "value": 190995000}, {"id": "3.4_pris", "name": "3.4 Prisons", "value": 166626000}, {"id": "8.2_cult", "name": "8.2 Cultural services", "value": 145930000}, {"id": "4.5_of_w", "name": "4.5 of which: local public transport", "value": 141078000}, {"id": "4.8_r&d_", "name": "4.8 R&D economic affairs", "value": 111429000}, {"id": "9.1_of_w", "name": "9.1 of which: primary education", "value": 98240000}, {"id": "10.3_sur", "name": "10.3 Survivors", "value": 93900000}, {"id": "3.2_fire", "name": "3.2 Fire-protection services", "value": 79096000}, {"id": "6.2_comm", "name": "6.2 Community development", "value": 78231000}, {"id": "5.6_envi", "name": "5.6 Environment protection n.e.c.", "value": 73781000}, {"id": "1.6_gene", "name": "1.6 General public services n.e.c.", "value": 71235000}, {"id": "9.5_educ", "name": "9.5 Education not definable by level", "value": 66159000}, {"id": "4.6_comm", "name": "4.6 Communication", "value": 59564000}, {"id": "8.4_reli", "name": "8.4 Religious and other community services", "value": 52132000}, {"id": "4.7_othe", "name": "4.7 Other industries", "value": 51910000}, {"id": "6.4_stre", "name": "6.4 Street lighting", "value": 44607000}, {"id": "9.1_of_w", "name": "9.1 of which: under fives", "value": 35649000}, {"id": "4.5_of_w", "name": "4.5 of which: national roads", "value": 25527000}, {"id": "4.3_fuel", "name": "4.3 Fuel and energy", "value": 24221000}, {"id": "4.5_of_w", "name": "4.5 of which: other transport", "value": 19748000}, {"id": "7.b_medi", "name": "7.B Medical research", "value": 13615000}, {"id": "8.1_recr", "name": "8.1 Recreational and sporting services", "value": 11156000}, {"id": "4.2_of_w", "name": "4.2 of which: forestry", "value": 6258000}, {"id": "4.4_mini", "name": "4.4 Mining, manufacturing and construction", "value": 1121000}, {"id": "6.5_r&d_", "name": "6.5 R&D housing and community amenities", "value": 628000}, {"id": "3.5_r&d_", "name": "3.5 R&D public order and safety", "value": 581000}, {"id": "4.2_of_w", "name": "4.2 of which: market support under CAP", "value": 316000}, {"id": "9.7_r&d_", "name": "9.7 R&D education", "value": 298000}, {"id": "1.5_r&d_", "name": "1.5 R&D general public services", "value": 82000}]}, {"id": "northe", "name": "Northern Ireland Transport Holding Company", "value": 252096000, "children": [{"id": "4.5_of_w", "name": "4.5 of which: railway", "value": 193164000}, {"id": "4.5_of_w", "name": "4.5 of which: local public transport", "value": 58932000}]}, {"id": "northe", "name": "Northern Ireland Trust Ports", "value": 39517000}, {"id": "driver", "name": "Driver and Vehicle Testing Agency", "value": 17139000}, {"id": "northe", "name": "Northern Ireland Housing Executive", "value": 4114000}]}, {"id": "tea", "name": "TEACHERS' PENSION SCHEME (ENGLAND AND WALES)", "value": 22053793000, "children": [{"id": "teache", "name": "Teachers' Pension Scheme (England & Wales)", "value": 22053793000, "children": [{"id": "10.2_old", "name": "10.2 Old age; of which: pensions", "value": 22064486000}, {"id": "n/a", "name": "n/a", "value": -10693000}]}]}, {"id": "wel", "name": "WELSH ASSEMBLY GOVERNMENT", "value": 20296312000, "children": [{"id": "welsh_", "name": "Welsh Assembly Government", "value": 20217199000, "children": [{"id": "7.a_medi", "name": "7.A Medical services", "value": 9859617000}, {"id": "1.6_gene", "name": "1.6 General public services n.e.c.", "value": 4601500000}, {"id": "n/a", "name": "n/a", "value": -2922906000}, {"id": "not_know", "name": "Not known", "value": 1057259000}, {"id": "9.2_seco", "name": "9.2 Secondary education", "value": 1039653000}, {"id": "4.5_of_w", "name": "4.5 of which: railway", "value": 931347000}, {"id": "6.1_of_w", "name": "6.1 of which: local authority housing", "value": 930154000}, {"id": "7.c_cent", "name": "7.C Central and other health services", "value": 453023000}, {"id": "9.4_tert", "name": "9.4 Tertiary education", "value": 418373000}, {"id": "4.5_of_w", "name": "4.5 of which: national roads", "value": 410358000}, {"id": "9.8_educ", "name": "9.8 Education n.e.c.", "value": 376533000}, {"id": "9.6_subs", "name": "9.6 Subsidiary services to education", "value": 327491000}, {"id": "10.7_soc", "name": "10.7 Social exclusion n.e.c.; of which: personal social services", "value": 299957000}, {"id": "4.2_of_w", "name": "4.2 of which: market support under CAP", "value": 260836000}, {"id": "9.1_of_w", "name": "9.1 of which: under fives", "value": 240460000}, {"id": "4.5_of_w", "name": "4.5 of which: local public transport", "value": 237602000}, {"id": "4.2_of_w", "name": "4.2 of which: other agriculture, food and fisheries policy", "value": 228993000}, {"id": "1.1_exec", "name": "1.1 Executive and legislative organs, financial and fiscal affairs, external affairs", "value": 211356000}, {"id": "5.6_envi", "name": "5.6 Environment protection n.e.c.", "value": 186704000}, {"id": "10.9_soc", "name": "10.9 Social protection n.e.c.", "value": 162372000}, {"id": "6.2_comm", "name": "6.2 Community development", "value": 161593000}, {"id": "4.1_gene", "name": "4.1 General economic, commercial and labour affairs", "value": 146129000}, {"id": "8.2_cult", "name": "8.2 Cultural services", "value": 141718000}, {"id": "10.4_fam", "name": "10.4 Family and children; of which: personal social services", "value": 94621000}, {"id": "9.5_educ", "name": "9.5 Education not definable by level", "value": 81459000}, {"id": "8.6_recr", "name": "8.6 Recreation, culture and religion n.e.c.", "value": 52936000}, {"id": "8.1_recr", "name": "8.1 Recreational and sporting services", "value": 51439000}, {"id": "7.b_medi", "name": "7.B Medical research", "value": 46617000}, {"id": "5.1_wast", "name": "5.1 Waste management", "value": 40990000}, {"id": "4.6_comm", "name": "4.6 Communication", "value": 30041000}, {"id": "4.7_othe", "name": "4.7 Other industries", "value": 21653000}, {"id": "4.8_r&d_", "name": "4.8 R&D economic affairs", "value": 18714000}, {"id": "3.2_fire", "name": "3.2 Fire-protection services", "value": 15972000}, {"id": "4.9_econ", "name": "4.9 Economic affairs n.e.c.", "value": 1705000}, {"id": "4.2_of_w", "name": "4.2 of which: forestry", "value": 930000}]}, {"id": "nation", "name": "National Assembly for Wales", "value": 62977000}, {"id": "wales_", "name": "Wales Audit Office", "value": 10795000}, {"id": "public", "name": "Public Service Ombudsman Wales", "value": 5341000}]}, {"id": "nor", "name": "NORTHERN IRELAND OFFICE", "value": 19800475000, "children": [{"id": "northe", "name": "Northern Ireland Office", "value": 19793259000, "children": [{"id": "n/a", "name": "n/a", "value": 19755000000}, {"id": "1.1_exec", "name": "1.1 Executive and legislative organs, financial and fiscal affairs, external affairs", "value": 38259000}]}, {"id": "ni_hum", "name": "NI Human Rights Commission", "value": 5036000, "children": [{"id": "1.1_exec", "name": "1.1 Executive and legislative organs, financial and fiscal affairs, external affairs", "value": 2519000}, {"id": "n/a", "name": "n/a", "value": 2517000}]}, {"id": "ni_par", "name": "NI Parades Commission", "value": 1513000}, {"id": "indepe", "name": "Independent Reporting Commission", "value": 667000, "children": [{"id": "1.1_exec", "name": "1.1 Executive and legislative organs, financial and fiscal affairs, external affairs", "value": 336000}, {"id": "n/a", "name": "n/a", "value": 331000}]}]}, {"id": "wal", "name": "WALES OFFICE", "value": 19594534000, "children": [{"id": "wales_", "name": "Wales Office", "value": 19594534000, "children": [{"id": "n/a", "name": "n/a", "value": 19589123000}, {"id": "1.1_exec", "name": "1.1 Executive and legislative organs, financial and fiscal affairs, external affairs", "value": 5411000}]}]}, {"id": "loc", "name": "LOCAL GOVERNMENT SCOTLAND", "value": 18825814000, "children": [{"id": "scotla", "name": "Scotland Local Authorities", "value": 17785174000, "children": [{"id": "9.1_of_w", "name": "9.1 of which: primary education", "value": 3784228000}, {"id": "9.2_seco", "name": "9.2 Secondary education", "value": 2908442000}, {"id": "10.2_old", "name": "10.2 Old age; of which: personal social services", "value": 1806299000}, {"id": "10.1_sic", "name": "10.1 Sickness and disability; of which: personal social services", "value": 1421628000}, {"id": "10.6_hou", "name": "10.6 Housing", "value": 1302389000}, {"id": "9.1_of_w", "name": "9.1 of which: under fives", "value": 1025194000}, {"id": "10.4_fam", "name": "10.4 Family and children; of which: personal social services", "value": 964083000}, {"id": "4.5_of_w", "name": "4.5 of which: local roads", "value": 886829000}, {"id": "5.1_wast", "name": "5.1 Waste management", "value": 705277000}, {"id": "1.1_exec", "name": "1.1 Executive and legislative organs, financial and fiscal affairs, external affairs", "value": 633163000}, {"id": "8.1_recr", "name": "8.1 Recreational and sporting services", "value": 551634000}, {"id": "4.1_gene", "name": "4.1 General economic, commercial and labour affairs", "value": 453276000}, {"id": "4.5_of_w", "name": "4.5 of which: other transport", "value": 314808000}, {"id": "6.1_of_w", "name": "6.1 of which: local authority housing", "value": 266096000}, {"id": "1.6_gene", "name": "1.6 General public services n.e.c.", "value": 132955000}, {"id": "9.5_educ", "name": "9.5 Education not definable by level", "value": 126083000}, {"id": "5.6_envi", "name": "5.6 Environment protection n.e.c.", "value": 118108000}, {"id": "8.2_cult", "name": "8.2 Cultural services", "value": 77245000}, {"id": "10.9_soc", "name": "10.9 Social protection n.e.c.", "value": 74033000}, {"id": "4.2_of_w", "name": "4.2 of which: other agriculture, food and fisheries policy", "value": 69839000}, {"id": "6.2_comm", "name": "6.2 Community development", "value": 57959000}, {"id": "9.8_educ", "name": "9.8 Education n.e.c.", "value": 35651000}, {"id": "4.7_othe", "name": "4.7 Other industries", "value": 25662000}, {"id": "8.4_reli", "name": "8.4 Religious and other community services", "value": 18863000}, {"id": "4.5_of_w", "name": "4.5 of which: local public transport", "value": 13761000}, {"id": "4.5_of_w", "name": "4.5 of which: railway", "value": 4327000}, {"id": "6.4_stre", "name": "6.4 Street lighting", "value": 3923000}, {"id": "2.2_civi", "name": "2.2 Civil defence", "value": 3419000}]}, {"id": "scotla", "name": "Scotland Housing Revenue Account", "value": 1040640000}]}, {"id": "hom", "name": "HOME OFFICE", "value": 17821833000, "children": [{"id": "home_o", "name": "Home Office", "value": 17705252000, "children": [{"id": "3.1_of_w", "name": "3.1 of which: other police services", "value": 12541465000}, {"id": "3.6_publ", "name": "3.6 Public order and safety n.e.c.", "value": 3963891000}, {"id": "3.1_of_w", "name": "3.1 of which: immigration and citizenship", "value": 1422324000}, {"id": "n/a", "name": "n/a", "value": -221948000}, {"id": "not_know", "name": "Not known", "value": -480000}]}, {"id": "indepe", "name": "Independent Police Complaints Commission", "value": 74753000}, {"id": "colleg", "name": "College of Policing", "value": 42915000}, {"id": "disclo", "name": "Disclosure and Barring Service (DBS)", "value": -15496000}, {"id": "gangma", "name": "Gangmasters Licensing Authority HOF034", "value": 5332000}, {"id": "securi", "name": "Security Industry Authority", "value": 4604000}, {"id": "office", "name": "Office of the Immigration Services Commissioner", "value": 4473000}]}, {"id": "cab", "name": "CABINET OFFICE: CIVIL SUPERANNUATION", "value": 15924238000, "children": [{"id": "cabine", "name": "Cabinet Office: Civil Superannuation", "value": 15924238000}]}, {"id": "dep", "name": "DEPARTMENT FOR CULTURE, MEDIA AND SPORT", "value": 14758490000, "children": [{"id": "bristi", "name": "Bristish Broadcasting Corporation", "value": 8706761000, "children": [{"id": "8.3_broa", "name": "8.3 Broadcasting and publishing services", "value": 4955563000}, {"id": "n/a", "name": "n/a", "value": 3751198000}]}, {"id": "arts_c", "name": "Arts Council", "value": 1064642000, "children": [{"id": "8.2_cult", "name": "8.2 Cultural services", "value": 540336000}, {"id": "n/a", "name": "n/a", "value": 524306000}]}, {"id": "big_lo", "name": "Big Lottery Fund", "value": 694016000, "children": [{"id": "10.9_soc", "name": "10.9 Social protection n.e.c.", "value": 651751000}, {"id": "5.6_envi", "name": "5.6 Environment protection n.e.c.", "value": 40808000}, {"id": "7.c_cent", "name": "7.C Central and other health services", "value": 1457000}]}, {"id": "birmin", "name": "Birmingham 2022", "value": 552661000, "children": [{"id": "n/a", "name": "n/a", "value": 302000000}, {"id": "8.1_recr", "name": "8.1 Recreational and sporting services", "value": 250661000}]}, {"id": "arts_c", "name": "Arts Council of England Lottery", "value": 446376000}, {"id": "depart", "name": "Department for Culture, Media and Sport", "value": 318673000, "children": [{"id": "8.4_reli", "name": "8.4 Religious and other community services", "value": 117779000}, {"id": "8.6_recr", "name": "8.6 Recreation, culture and religion n.e.c.", "value": 106303000}, {"id": "6.2_comm", "name": "6.2 Community development", "value": 51106000}, {"id": "8.3_broa", "name": "8.3 Broadcasting and publishing services", "value": 24932000}, {"id": "8.1_recr", "name": "8.1 Recreational and sporting services", "value": 11844000}, {"id": "8.2_cult", "name": "8.2 Cultural services", "value": 5083000}, {"id": "8.5_r&d_", "name": "8.5 R&D recreation, culture and religion", "value": 1516000}, {"id": "4.6_comm", "name": "4.6 Communication", "value": 110000}]}, {"id": "sport_", "name": "Sport England", "value": 270175000, "children": [{"id": "8.1_recr", "name": "8.1 Recreational and sporting services", "value": 156604000}, {"id": "n/a", "name": "n/a", "value": 113571000}]}, {"id": "librar", "name": "Libraries (Subgroup)", "value": 251600000, "children": [{"id": "8.2_cult", "name": "8.2 Cultural services", "value": 135058000}, {"id": "n/a", "name": "n/a", "value": 116542000}]}, {"id": "englis", "name": "English Heritage", "value": 230167000, "children": [{"id": "8.2_cult", "name": "8.2 Cultural services", "value": 118940000}, {"id": "n/a", "name": "n/a", "value": 111227000}]}, {"id": "herita", "name": "Heritage Lottery Fund", "value": 214718000}, {"id": "britis", "name": "British Museum", "value": 214565000, "children": [{"id": "8.2_cult", "name": "8.2 Cultural services", "value": 146798000}, {"id": "n/a", "name": "n/a", "value": 67767000}]}, {"id": "united", "name": "United Kingdom Sports Council", "value": 193176000, "children": [{"id": "8.1_recr", "name": "8.1 Recreational and sporting services", "value": 102796000}, {"id": "n/a", "name": "n/a", "value": 90380000}]}, {"id": "nation", "name": "National Museum of Science and Industry", "value": 175089000, "children": [{"id": "8.2_cult", "name": "8.2 Cultural services", "value": 94797000}, {"id": "n/a", "name": "n/a", "value": 80292000}]}, {"id": "nation", "name": "National Citizen Service", "value": 142623000, "children": [{"id": "6.2_comm", "name": "6.2 Community development", "value": 73628000}, {"id": "n/a", "name": "n/a", "value": 68995000}]}, {"id": "victor", "name": "Victoria and Albert Museum", "value": 141533000, "children": [{"id": "8.2_cult", "name": "8.2 Cultural services", "value": 74082000}, {"id": "n/a", "name": "n/a", "value": 67451000}]}, {"id": "natura", "name": "Natural History Museum", "value": 139001000, "children": [{"id": "8.2_cult", "name": "8.2 Cultural services", "value": 73113000}, {"id": "n/a", "name": "n/a", "value": 65888000}]}, {"id": "sport_", "name": "Sport England Lottery", "value": 137793000}, {"id": "uk_fil", "name": "UK Film Council Lottery", "value": 105842000}, {"id": "tate_g", "name": "Tate Gallery", "value": 105324000, "children": [{"id": "n/a", "name": "n/a", "value": 54156000}, {"id": "8.2_cult", "name": "8.2 Cultural services", "value": 51168000}]}, {"id": "visit_", "name": "Visit Britain", "value": 103281000, "children": [{"id": "4.7_othe", "name": "4.7 Other industries", "value": 55136000}, {"id": "n/a", "name": "n/a", "value": 48145000}]}, {"id": "museum", "name": "Museums and Gallaries (Subgroup)", "value": 102472000, "children": [{"id": "8.2_cult", "name": "8.2 Cultural services", "value": 58540000}, {"id": "n/a", "name": "n/a", "value": 43932000}]}, {"id": "nation", "name": "National Gallery", "value": 67664000, "children": [{"id": "8.2_cult", "name": "8.2 Cultural services", "value": 36951000}, {"id": "n/a", "name": "n/a", "value": 30713000}]}, {"id": "imperi", "name": "Imperial War Museum", "value": 66226000, "children": [{"id": "n/a", "name": "n/a", "value": 33203000}, {"id": "8.2_cult", "name": "8.2 Cultural services", "value": 33023000}]}, {"id": "britis", "name": "British Film Institute", "value": 62794000, "children": [{"id": "n/a", "name": "n/a", "value": 34515000}, {"id": "8.3_broa", "name": "8.3 Broadcasting and publishing services", "value": 28279000}]}, {"id": "nation", "name": "National Lottery: UK Sport Lottery", "value": 57815000}, {"id": "nation", "name": "National Museums Liverpool", "value": 57546000, "children": [{"id": "8.2_cult", "name": "8.2 Cultural services", "value": 31268000}, {"id": "n/a", "name": "n/a", "value": 26278000}]}, {"id": "nation", "name": "National Maritime Museum", "value": 46064000, "children": [{"id": "8.2_cult", "name": "8.2 Cultural services", "value": 26112000}, {"id": "n/a", "name": "n/a", "value": 19952000}]}, {"id": "nation", "name": "National Lottery Commission", "value": 43577000, "children": [{"id": "n/a", "name": "n/a", "value": 21862000}, {"id": "8.6_recr", "name": "8.6 Recreation, culture and religion n.e.c.", "value": 21715000}]}, {"id": "united", "name": "United Kingdom Anti Doping", "value": 19815000, "children": [{"id": "8.1_recr", "name": "8.1 Recreational and sporting services", "value": 10252000}, {"id": "n/a", "name": "n/a", "value": 9563000}]}, {"id": "nation", "name": "National Heritage Memorial Fund", "value": 18419000}, {"id": "church", "name": "Churches Conservation Trust", "value": 5796000, "children": [{"id": "n/a", "name": "n/a", "value": 2903000}, {"id": "8.2_cult", "name": "8.2 Cultural services", "value": 2893000}]}, {"id": "the_ga", "name": "The Gambling Commission", "value": -4315000, "children": [{"id": "8.1_recr", "name": "8.1 Recreational and sporting services", "value": -5052000}, {"id": "n/a", "name": "n/a", "value": 737000}]}, {"id": "footba", "name": "Football Licensing Authority", "value": 3347000, "children": [{"id": "8.1_recr", "name": "8.1 Recreational and sporting services", "value": 1679000}, {"id": "n/a", "name": "n/a", "value": 1668000}]}, {"id": "s4c", "name": "S4C", "value": 3252000}, {"id": "inform", "name": "Information Commission DCMS", "value": 2000}, {"id": "ofcom_", "name": "Ofcom DCMS", "value": 0}]}, {"id": "dep", "name": "DEPARTMENT FOR SCIENCE, INNOVATION AND TECHNOLOGY", "value": 11668199000, "children": [{"id": "uk_res", "name": "UK Research and Innovation", "value": 9396959000, "children": [{"id": "4.8_r&d_", "name": "4.8 R&D economic affairs", "value": 6026151000}, {"id": "9.7_r&d_", "name": "9.7 R&D education", "value": 2970014000}, {"id": "5.5_r&d_", "name": "5.5 R&D environment protection", "value": 205736000}, {"id": "7.b_medi", "name": "7.B Medical research", "value": 162718000}, {"id": "8.5_r&d_", "name": "8.5 R&D recreation, culture and religion", "value": 32340000}]}, {"id": "depart", "name": "Department for Science, Innovation and Technology", "value": 2074124000, "children": [{"id": "4.8_r&d_", "name": "4.8 R&D economic affairs", "value": 1135666000}, {"id": "4.1_gene", "name": "4.1 General economic, commercial and labour affairs", "value": 222290000}, {"id": "4.6_comm", "name": "4.6 Communication", "value": 180160000}, {"id": "1.1_exec", "name": "1.1 Executive and legislative organs, financial and fiscal affairs, external affairs", "value": 170641000}, {"id": "4.9_econ", "name": "4.9 Economic affairs n.e.c.", "value": 131299000}, {"id": "1.3_gene", "name": "1.3 General services", "value": 91818000}, {"id": "8.3_broa", "name": "8.3 Broadcasting and publishing services", "value": 82092000}, {"id": "8.5_r&d_", "name": "8.5 R&D recreation, culture and religion", "value": 62709000}, {"id": "5.3_poll", "name": "5.3 Pollution abatement", "value": -2551000}]}, {"id": "diamon", "name": "Diamond Light Source Limited", "value": 104770000}, {"id": "rc_uk_", "name": "RC UK Shared Services Centre Limited", "value": 54355000, "children": [{"id": "1.3_gene", "name": "1.3 General services", "value": 53661000}, {"id": "4.9_econ", "name": "4.9 Economic affairs n.e.c.", "value": 694000}]}, {"id": "nation", "name": "National Endowment for Science, Technology and the Arts", "value": 47200000}, {"id": "britis", "name": "British Business Bank plc BEIS", "value": -24506000}, {"id": "inform", "name": "Information Commission", "value": 12455000}, {"id": "bis_(p", "name": "BIS (Postal Services Act 2011) Company Limited BEIS", "value": -4975000}, {"id": "britis", "name": "British Technology Investments", "value": 4924000}, {"id": "ofcom", "name": "Ofcom", "value": 2576000}, {"id": "advanc", "name": "Advanced Research and Invention Agency", "value": 375000}, {"id": "oil_&_", "name": "Oil & Gas Authority BEIS", "value": -58000}, {"id": "civil_", "name": "Civil Nuclear Police Authority and Constabulary BEIS", "value": 0}, {"id": "compet", "name": "Competition Service BEIS", "value": 0}, {"id": "financ", "name": "Financial Reporting Council Limited BEIS", "value": 0}, {"id": "adviso", "name": "Advisory, Conciliation and Arbitration Service BEIS", "value": 0}, {"id": "low_ca", "name": "Low Carbon Contracts Company BEIS", "value": 0}, {"id": "nnb_ho", "name": "NNB Holding Company (SZC) LTD (GenCo) BEIS", "value": 0}, {"id": "salix_", "name": "Salix BEIS", "value": 0}, {"id": "nuclea", "name": "Nuclear Decommissioning Authority BEIS", "value": 0}, {"id": "united", "name": "United Kingdom Atomic Energy Authority BEIS", "value": 0}, {"id": "coal_a", "name": "Coal Authority BEIS", "value": 0}, {"id": "enrich", "name": "Enrichment Holdings Ltd BEIS", "value": 0}, {"id": "cornwa", "name": "Cornwall and Isles of Scilly Investments Limited BEIS", "value": 0}, {"id": "midlan", "name": "Midlands Engine Investment Limited BEIS", "value": 0}, {"id": "northe", "name": "Northern Powerhouse Investment Limited BEIS", "value": 0}, {"id": "uk_gre", "name": "UK Green Investment Platform Entity BEIS", "value": 0}, {"id": "electr", "name": "Electricity Settlements Company BEIS", "value": 0}, {"id": "fleetb", "name": "Fleetbank Funding Limited BEIS", "value": 0}, {"id": "commit", "name": "Committee on Climate Change BEIS", "value": 0}]}, {"id": "min", "name": "MINISTRY OF JUSTICE", "value": 11567555000, "children": [{"id": "minist", "name": "Ministry of Justice", "value": 11243754000, "children": [{"id": "3.3_law_", "name": "3.3 Law courts", "value": 5803348000}, {"id": "3.4_pris", "name": "3.4 Prisons", "value": 5440406000}]}, {"id": "childr", "name": "Children and Family Court Advisory and Support Service", "value": 177109000}, {"id": "youth_", "name": "Youth Justice Board for England and Wales", "value": 101476000}, {"id": "parole", "name": "Parole Board for England and Wales", "value": 23552000}, {"id": "judici", "name": "Judicial Appointments Commission", "value": 8773000}, {"id": "crimin", "name": "Criminal Cases Review Commission", "value": 7700000}, {"id": "indepe", "name": "Independent Monitoring Authority for the Citizens\u2019 Rights Agreements", "value": 4887000}, {"id": "office", "name": "Office for Legal Complaints", "value": 299000}, {"id": "legal_", "name": "Legal Services Board", "value": 5000}, {"id": "gov_fa", "name": "Gov Facility Services Limited", "value": 0}]}, {"id": "loc", "name": "LOCAL GOVERNMENT WALES", "value": 11113462000, "children": [{"id": "wales_", "name": "Wales Local Authorities", "value": 10789314000, "children": [{"id": "9.1_of_w", "name": "9.1 of which: primary education", "value": 2150012000}, {"id": "9.2_seco", "name": "9.2 Secondary education", "value": 1537766000}, {"id": "10.6_hou", "name": "10.6 Housing", "value": 1087837000}, {"id": "10.4_fam", "name": "10.4 Family and children; of which: personal social services", "value": 958585000}, {"id": "3.1_of_w", "name": "3.1 of which: other police services", "value": 916754000}, {"id": "10.2_old", "name": "10.2 Old age; of which: personal social services", "value": 873702000}, {"id": "10.1_sic", "name": "10.1 Sickness and disability; of which: personal social services", "value": 828669000}, {"id": "5.1_wast", "name": "5.1 Waste management", "value": 412138000}, {"id": "4.5_of_w", "name": "4.5 of which: local roads", "value": 356037000}, {"id": "8.1_recr", "name": "8.1 Recreational and sporting services", "value": 217224000}, {"id": "6.2_comm", "name": "6.2 Community development", "value": 198994000}, {"id": "3.2_fire", "name": "3.2 Fire-protection services", "value": 187444000}, {"id": "1.1_exec", "name": "1.1 Executive and legislative organs, financial and fiscal affairs, external affairs", "value": 180491000}, {"id": "1.6_gene", "name": "1.6 General public services n.e.c.", "value": 111869000}, {"id": "4.5_of_w", "name": "4.5 of which: local public transport", "value": 99500000}, {"id": "4.1_gene", "name": "4.1 General economic, commercial and labour affairs", "value": 92676000}, {"id": "8.2_cult", "name": "8.2 Cultural services", "value": 91082000}, {"id": "6.1_of_w", "name": "6.1 of which: local authority housing", "value": 79372000}, {"id": "5.6_envi", "name": "5.6 Environment protection n.e.c.", "value": 58417000}, {"id": "9.5_educ", "name": "9.5 Education not definable by level", "value": 53206000}, {"id": "4.2_of_w", "name": "4.2 of which: other agriculture, food and fisheries policy", "value": 46556000}, {"id": "9.1_of_w", "name": "9.1 of which: under fives", "value": 45607000}, {"id": "6.4_stre", "name": "6.4 Street lighting", "value": 37200000}, {"id": "4.5_of_w", "name": "4.5 of which: other transport", "value": 31466000}, {"id": "10.7_soc", "name": "10.7 Social exclusion n.e.c.; of which: personal social services", "value": 26802000}, {"id": "9.6_subs", "name": "9.6 Subsidiary services to education", "value": 25228000}, {"id": "4.7_othe", "name": "4.7 Other industries", "value": 20643000}, {"id": "10.9_soc", "name": "10.9 Social protection n.e.c.", "value": 20024000}, {"id": "4.4_mini", "name": "4.4 Mining, manufacturing and construction", "value": 13569000}, {"id": "3.3_law_", "name": "3.3 Law courts", "value": 8218000}, {"id": "9.8_educ", "name": "9.8 Education n.e.c.", "value": 7097000}, {"id": "2.2_civi", "name": "2.2 Civil defence", "value": 6286000}, {"id": "1.3_gene", "name": "1.3 General services", "value": 4575000}, {"id": "5.4_prot", "name": "5.4 Protection of biodiversity and landscape", "value": 4564000}, {"id": "8.4_reli", "name": "8.4 Religious and other community services", "value": -696000}, {"id": "8.6_recr", "name": "8.6 Recreation, culture and religion n.e.c.", "value": 400000}]}, {"id": "wales_", "name": "Wales Housing Revenue Account", "value": 324148000}]}, {"id": "for", "name": "FOREIGN, COMMONWEALTH AND DEVELOPMENT OFFICE", "value": 9026908000, "children": [{"id": "foreig", "name": "Foreign, Commonwealth and Development Office", "value": 8944142000, "children": [{"id": "1.2_fore", "name": "1.2 Foreign economic aid", "value": 6228862000}, {"id": "1.1_exec", "name": "1.1 Executive and legislative organs, financial and fiscal affairs, external affairs", "value": 3770864000}, {"id": "n/a", "name": "n/a", "value": -1364934000}, {"id": "1.5_r&d_", "name": "1.5 R&D general public services", "value": 309350000}]}, {"id": "common", "name": "Commonwealth Scholarship Commission", "value": 56438000, "children": [{"id": "1.2_fore", "name": "1.2 Foreign economic aid", "value": 28219000}, {"id": "n/a", "name": "n/a", "value": 28219000}]}, {"id": "westmi", "name": "Westminster Foundation for Democracy", "value": 13052000, "children": [{"id": "1.1_exec", "name": "1.1 Executive and legislative organs, financial and fiscal affairs, external affairs", "value": 6526000}, {"id": "n/a", "name": "n/a", "value": 6526000}]}, {"id": "indepe", "name": "Independent Commission for Aid Impact", "value": 7190000, "children": [{"id": "1.2_fore", "name": "1.2 Foreign economic aid", "value": 3595000}, {"id": "n/a", "name": "n/a", "value": 3595000}]}, {"id": "marsha", "name": "Marshall Aid Commemoration Commission", "value": 5406000, "children": [{"id": "1.1_exec", "name": "1.1 Executive and legislative organs, financial and fiscal affairs, external affairs", "value": 2703000}, {"id": "n/a", "name": "n/a", "value": 2703000}]}, {"id": "great_", "name": "Great Britain China Centre", "value": 680000, "children": [{"id": "1.1_exec", "name": "1.1 Executive and legislative organs, financial and fiscal affairs, external affairs", "value": 340000}, {"id": "n/a", "name": "n/a", "value": 340000}]}]}, {"id": "arm", "name": "ARMED FORCES PENSION AND COMPENSATION SCHEMES", "value": 8470744000, "children": [{"id": "armed_", "name": "Armed Forces Pension and Compensation Schemes", "value": 8470744000, "children": [{"id": "10.2_old", "name": "10.2 Old age; of which: pensions", "value": 8502129000}, {"id": "n/a", "name": "n/a", "value": -31385000}]}]}, {"id": "dep", "name": "DEPARTMENT FOR ENVIRONMENT, FOOD AND RURAL AFFAIRS", "value": 7508246000, "children": [{"id": "depart", "name": "Department for Environment, Food and Rural Affairs", "value": 3835105000, "children": [{"id": "4.2_of_w", "name": "4.2 of which: market support under CAP", "value": 1885709000}, {"id": "4.2_of_w", "name": "4.2 of which: other agriculture, food and fisheries policy", "value": 1304772000}, {"id": "5.4_prot", "name": "5.4 Protection of biodiversity and landscape", "value": 182516000}, {"id": "n/a", "name": "n/a", "value": 136098000}, {"id": "4.2_of_w", "name": "4.2 of which: forestry", "value": 102159000}, {"id": "4.8_r&d_", "name": "4.8 R&D economic affairs", "value": 101724000}, {"id": "1.2_fore", "name": "1.2 Foreign economic aid", "value": 100154000}, {"id": "5.6_envi", "name": "5.6 Environment protection n.e.c.", "value": -98137000}, {"id": "5.3_poll", "name": "5.3 Pollution abatement", "value": 64395000}, {"id": "5.1_wast", "name": "5.1 Waste management", "value": 23457000}, {"id": "5.5_r&d_", "name": "5.5 R&D environment protection", "value": 19523000}, {"id": "1.5_r&d_", "name": "1.5 R&D general public services", "value": 12735000}]}, {"id": "enviro", "name": "Environment Agency", "value": 3099772000, "children": [{"id": "5.6_envi", "name": "5.6 Environment protection n.e.c.", "value": 1743711000}, {"id": "4.2_of_w", "name": "4.2 of which: other agriculture, food and fisheries policy", "value": 1343629000}, {"id": "5.5_r&d_", "name": "5.5 R&D environment protection", "value": 12432000}]}, {"id": "natura", "name": "Natural England", "value": 394413000, "children": [{"id": "5.4_prot", "name": "5.4 Protection of biodiversity and landscape", "value": 204413000}, {"id": "4.2_of_w", "name": "4.2 of which: other agriculture, food and fisheries policy", "value": 190000000}]}, {"id": "royal_", "name": "Royal Botanic Gardens, Kew", "value": 97565000, "children": [{"id": "5.4_prot", "name": "5.4 Protection of biodiversity and landscape", "value": 49650000}, {"id": "4.2_of_w", "name": "4.2 of which: other agriculture, food and fisheries policy", "value": 47915000}]}, {"id": "flood_", "name": "Flood Re", "value": -81745000}, {"id": "marine", "name": "Marine Management Organisation", "value": 61907000}, {"id": "joint_", "name": "Joint Nature Conservation Committee", "value": 39481000, "children": [{"id": "5.4_prot", "name": "5.4 Protection of biodiversity and landscape", "value": 20050000}, {"id": "4.2_of_w", "name": "4.2 of which: other agriculture, food and fisheries policy", "value": 19431000}]}, {"id": "office", "name": "Office for Environmental Protection", "value": 17228000, "children": [{"id": "5.6_envi", "name": "5.6 Environment protection n.e.c.", "value": 9545000}, {"id": "4.2_of_w", "name": "4.2 of which: other agriculture, food and fisheries policy", "value": 7683000}]}, {"id": "consum", "name": "Consumer Council for Water", "value": 14110000, "children": [{"id": "4.2_of_w", "name": "4.2 of which: other agriculture, food and fisheries policy", "value": 7060000}, {"id": "6.3_wate", "name": "6.3 Water supply", "value": 7050000}]}, {"id": "sea_fi", "name": "Sea Fish Industry Authority", "value": 12176000}, {"id": "agricu", "name": "Agriculture & Horticulture Development Board", "value": 7616000}, {"id": "nation", "name": "National Forest Company", "value": 7570000, "children": [{"id": "4.2_of_w", "name": "4.2 of which: forestry", "value": 3941000}, {"id": "4.2_of_w", "name": "4.2 of which: other agriculture, food and fisheries policy", "value": 3629000}]}, {"id": "covent", "name": "Covent Garden Market Authority", "value": 3048000}]}, {"id": "dep", "name": "DEPARTMENT FOR BUSINESS AND TRADE", "value": 3662982000, "children": [{"id": "depart", "name": "Department for Business and Trade", "value": 2795252000, "children": [{"id": "4.1_gene", "name": "4.1 General economic, commercial and labour affairs", "value": 1905915000}, {"id": "4.9_econ", "name": "4.9 Economic affairs n.e.c.", "value": 402378000}, {"id": "4.8_r&d_", "name": "4.8 R&D economic affairs", "value": 370746000}, {"id": "4.5_of_w", "name": "4.5 of which: other transport", "value": -319405000}, {"id": "10.5_une", "name": "10.5 Unemployment; of which: other unemployment benefits", "value": 263148000}, {"id": "10.4_fam", "name": "10.4 Family and children; of which: family benefits, income support and tax credits", "value": 100000000}, {"id": "n/a", "name": "n/a", "value": 62882000}, {"id": "4.6_comm", "name": "4.6 Communication", "value": -53597000}, {"id": "not_know", "name": "Not known", "value": 30043000}, {"id": "1.1_exec", "name": "1.1 Executive and legislative organs, financial and fiscal affairs, external affairs", "value": 22681000}, {"id": "4.4_mini", "name": "4.4 Mining, manufacturing and construction", "value": 16662000}, {"id": "1.2_fore", "name": "1.2 Foreign economic aid", "value": -6201000}]}, {"id": "britis", "name": "British Business Bank plc", "value": 553603000}, {"id": "fleetb", "name": "Fleetbank Funding Limited", "value": 126904000, "children": [{"id": "not_know", "name": "Not known", "value": 145730000}, {"id": "4.1_gene", "name": "4.1 General economic, commercial and labour affairs", "value": -18826000}]}, {"id": "adviso", "name": "Advisory, Conciliation and Arbitration Service", "value": 59083000}, {"id": "midlan", "name": "Midlands Engine Investments Limited", "value": 47715000}, {"id": "bis_(p", "name": "BIS (Postal Services Act 2011) Company Limited", "value": 41686000, "children": [{"id": "4.6_comm", "name": "4.6 Communication", "value": 24719000}, {"id": "n/a", "name": "n/a", "value": 16967000}]}, {"id": "trade_", "name": "Trade Remedies Authority (TRA)", "value": 16380000}, {"id": "cornwa", "name": "Cornwall and Isles of Scilly Investments Limited", "value": 9193000}, {"id": "northe", "name": "Northern Powerhouse Investments Limited", "value": 7132000}, {"id": "compet", "name": "Competition Service", "value": 5591000}, {"id": "financ", "name": "Financial Reporting Council Limited", "value": 443000}]}, {"id": "cab", "name": "CABINET OFFICE", "value": 1120829000, "children": [{"id": "cabine", "name": "Cabinet Office", "value": 1120829000, "children": [{"id": "1.1_exec", "name": "1.1 Executive and legislative organs, financial and fiscal affairs, external affairs", "value": 798172000}, {"id": "1.3_gene", "name": "1.3 General services", "value": 301913000}, {"id": "4.1_gene", "name": "4.1 General economic, commercial and labour affairs", "value": 20744000}]}]}, {"id": "loc", "name": "LOCAL GOVERNMENT NORTHERN IRELAND", "value": 883859000, "children": [{"id": "northe", "name": "Northern Ireland Local Authorities", "value": 883859000, "children": [{"id": "6.6_hous", "name": "6.6 Housing and community amenities n.e.c.", "value": 253395000}, {"id": "5.1_wast", "name": "5.1 Waste management", "value": 252329000}, {"id": "8.1_recr", "name": "8.1 Recreational and sporting services", "value": 176772000}, {"id": "8.2_cult", "name": "8.2 Cultural services", "value": 70272000}, {"id": "7.c_cent", "name": "7.C Central and other health services", "value": 60507000}, {"id": "4.1_gene", "name": "4.1 General economic, commercial and labour affairs", "value": 39792000}, {"id": "6.2_comm", "name": "6.2 Community development", "value": 30792000}]}]}, {"id": "roy", "name": "ROYAL MAIL STATUTORY PENSION SCHEME", "value": 876996000, "children": [{"id": "royal_", "name": "Royal Mail Statutory Pension Scheme", "value": 876996000}]}, {"id": "nat", "name": "NATIONAL CRIME AGENCY", "value": 745436000, "children": [{"id": "nation", "name": "National Crime Agency", "value": 745436000}]}, {"id": "cro", "name": "CROWN PROSECUTION SERVICE", "value": 725398000, "children": [{"id": "the_cr", "name": "The Crown Prosecution Service", "value": 725398000}]}, {"id": "hou", "name": "HOUSE OF COMMONS: ADMINISTRATION", "value": 579818000, "children": [{"id": "house_", "name": "House of Commons: Administration", "value": 579818000}]}, {"id": "the", "name": "THE STATISTICS BOARD", "value": 384126000, "children": [{"id": "statis", "name": "Statistics Board", "value": 384126000}]}, {"id": "exp", "name": "EXPORT CREDITS GUARANTEE DEPARTMENT", "value": -257792000, "children": [{"id": "export", "name": "Export Credits Guarantee Department", "value": -257792000, "children": [{"id": "4.1_gene", "name": "4.1 General economic, commercial and labour affairs", "value": -202055000}, {"id": "n/a", "name": "n/a", "value": -55737000}]}]}, {"id": "hou", "name": "HOUSE OF LORDS", "value": 244325000, "children": [{"id": "house_", "name": "House of Lords", "value": 244325000, "children": [{"id": "1.1_exec", "name": "1.1 Executive and legislative organs, financial and fiscal affairs, external affairs", "value": 252444000}, {"id": "n/a", "name": "n/a", "value": -8119000}]}]}, {"id": "uni", "name": "UNITED KINGDOM ATOMIC ENERGY AUTHORITY PENSION SCHEMES", "value": 242769000, "children": [{"id": "depart", "name": "Department for Energy Security and Net Zero: UKAEA Pension Schemes", "value": 242769000, "children": [{"id": "10.2_old", "name": "10.2 Old age; of which: pensions", "value": 240901000}, {"id": "n/a", "name": "n/a", "value": 1868000}]}]}, {"id": "ind", "name": "INDEPENDENT PARLIAMENTARY STANDARDS AUTHORITY", "value": 231638000, "children": [{"id": "indepe", "name": "Independent Parliamentary Standards Authority", "value": 231638000}]}, {"id": "nat", "name": "NATIONAL SAVINGS AND INVESTMENTS", "value": 189303000, "children": [{"id": "nation", "name": "National Savings and Investments", "value": 189303000, "children": [{"id": "1.1_exec", "name": "1.1 Executive and legislative organs, financial and fiscal affairs, external affairs", "value": 177526000}, {"id": "n/a", "name": "n/a", "value": 11777000}]}]}, {"id": "off", "name": "OFFICE FOR STANDARDS IN EDUCATION, CHILDREN'S SERVICES AND SKILLS", "value": 155593000, "children": [{"id": "office", "name": "Office for Standards in Education, Children's Services and Skills", "value": 155593000}]}, {"id": "foo", "name": "FOOD STANDARDS AGENCY", "value": 131066000, "children": [{"id": "food_s", "name": "Food Standards Agency", "value": 131066000, "children": [{"id": "4.2_of_w", "name": "4.2 of which: other agriculture, food and fisheries policy", "value": 119215000}, {"id": "4.8_r&d_", "name": "4.8 R&D economic affairs", "value": 6860000}, {"id": "n/a", "name": "n/a", "value": 4991000}]}]}, {"id": "hm", "name": "HM LAND REGISTRY", "value": 116497000, "children": [{"id": "hm_lan", "name": "HM Land Registry", "value": 116497000}]}, {"id": "com", "name": "COMPETITION AND MARKETS AUTHORITY", "value": 112789000, "children": [{"id": "compet", "name": "Competition and Markets Authority", "value": 112789000}]}, {"id": "min", "name": "MINISTRY OF JUSTICE: JUDICIAL PENSIONS SCHEME", "value": 111138000, "children": [{"id": "minist", "name": "Ministry of Justice: Judicial Pensions Scheme", "value": 111138000}]}, {"id": "nat", "name": "NATIONAL AUDIT OFFICE", "value": 91148000, "children": [{"id": "nation", "name": "National Audit Office", "value": 91148000, "children": [{"id": "1.1_exec", "name": "1.1 Executive and legislative organs, financial and fiscal affairs, external affairs", "value": 91476000}, {"id": "n/a", "name": "n/a", "value": -328000}]}]}, {"id": "par", "name": "PARLIAMENTARY WORKS GRANT", "value": 80150000, "children": [{"id": "parlia", "name": "Parliamentary Works Grant", "value": 80150000}]}, {"id": "ser", "name": "SERIOUS FRAUD OFFICE", "value": 73870000, "children": [{"id": "seriou", "name": "Serious Fraud Office", "value": 73870000}]}, {"id": "the", "name": "THE NATIONAL ARCHIVES", "value": 51467000, "children": [{"id": "the_na", "name": "The National Archives", "value": 51467000}]}, {"id": "off", "name": "OFFICE OF THE PARLIAMENTARY COMMISSIONER FOR ADMINISTRATION AND THE HEALTH SERVICE COMMISSIONER FOR ENGLAND", "value": 50238000, "children": [{"id": "office", "name": "Office of the Parliamentary Commissioner for Administration and Health Services in England", "value": 50238000}]}, {"id": "wat", "name": "WATER SERVICES REGULATION AUTHORITY", "value": 35393000, "children": [{"id": "water_", "name": "Water Services Regulation Authority", "value": 35393000}]}, {"id": "cha", "name": "CHARITY COMMISSION", "value": 35046000, "children": [{"id": "charit", "name": "Charity Commission", "value": 35046000}]}, {"id": "off", "name": "OFFICE OF QUALIFICATIONS AND EXAMINATIONS REGULATION", "value": 28977000, "children": [{"id": "office", "name": "Office of Qualifications and Examinations Regulation", "value": 28977000}]}, {"id": "ele", "name": "ELECTORAL COMMISSION", "value": 24922000, "children": [{"id": "electo", "name": "Electoral Commission", "value": 24922000, "children": [{"id": "1.6_gene", "name": "1.6 General public services n.e.c.", "value": 25963000}, {"id": "n/a", "name": "n/a", "value": -1041000}]}]}, {"id": "hou", "name": "HOUSE OF COMMONS: MEMBERS", "value": 17434000, "children": [{"id": "house_", "name": "House of Commons: Members", "value": 17434000}]}, {"id": "hm", "name": "HM PROCURATOR GENERAL AND TREASURY SOLICITOR", "value": 12660000, "children": [{"id": "hm_pro", "name": "HM Procurator General and Treasury Solicitor", "value": 12660000, "children": [{"id": "n/a", "name": "n/a", "value": 11634000}, {"id": "3.3_law_", "name": "3.3 Law courts", "value": 1026000}]}]}, {"id": "for", "name": "FOREIGN, COMMONWEALTH AND DEVELOPMENT OFFICE: OVERSEAS SUPERANNUATION", "value": 9530000, "children": [{"id": "depart", "name": "Department for International Development: Overseas Superannuation", "value": 9530000}]}, {"id": "off", "name": "OFFICE OF GAS AND ELECTRICITY MARKETS", "value": 9529000, "children": [{"id": "office", "name": "Office of Gas and Electricity Markets", "value": 9529000}]}, {"id": "uni", "name": "UNITED KINGDOM SUPREME COURT", "value": 7022000, "children": [{"id": "united", "name": "United Kingdom Supreme Court", "value": 7022000}]}, {"id": "off", "name": "OFFICE OF RAIL AND ROAD", "value": 3884000, "children": [{"id": "office", "name": "Office of Rail Regulation", "value": 3884000, "children": [{"id": "n/a", "name": "n/a", "value": 3427000}, {"id": "4.5_of_w", "name": "4.5 of which: railway", "value": 457000}]}]}, {"id": "loc", "name": "LOCAL GOVERNMENT BOUNDARY COMMISSION FOR ENGLAND", "value": 2391000, "children": [{"id": "local_", "name": "Local Government Boundary Commission for England", "value": 2391000}]}, {"id": "cro", "name": "CROWN ESTATE OFFICE", "value": 2357000, "children": [{"id": "crown_", "name": "Crown Estate Office", "value": 2357000}]}, {"id": "gov", "name": "GOVERNMENT ACTUARY'S DEPARTMENT", "value": -406000, "children": [{"id": "govern", "name": "Government Actuary's Department", "value": -406000, "children": [{"id": "1.1_exec", "name": "1.1 Executive and legislative organs, financial and fiscal affairs, external affairs", "value": -692000}, {"id": "n/a", "name": "n/a", "value": 286000}]}]}]}