{
  "name": "France Collectivités Territoriales 2016",
  "id": "fr_collectivites",
  "value": 245295700000,
  "year": 2016,
  "source": "Eurostat gov_10a_exp, sector S1313 (Local government), France, COFOG classification",
  "note": "Total expenditure by French local governments (régions, départements, communes, EPCI). Eurostat ESA2010 accrual basis. Not consolidated against central government.",
  "children": [
    {
      "id": "fr_ct_gf10",
      "name": "Social Protection",
      "name_fr": "Protection sociale",
      "value": 47448500000
    },
    {
      "id": "fr_ct_gf01",
      "name": "General Public Services",
      "name_fr": "Services généraux des administrations publiques",
      "value": 46948500000
    },
    {
      "id": "fr_ct_gf04",
      "name": "Economic Affairs",
      "name_fr": "Affaires économiques",
      "value": 46527300000
    },
    {
      "id": "fr_ct_gf09",
      "name": "Education",
      "name_fr": "Enseignement",
      "value": 37173600000
    },
    {
      "id": "fr_ct_gf08",
      "name": "Recreation, Culture & Religion",
      "name_fr": "Loisirs, culture et culte",
      "value": 21434700000
    },
    {
      "id": "fr_ct_gf06",
      "name": "Housing & Community",
      "name_fr": "Logement et équipements collectifs",
      "value": 18905900000
    },
    {
      "id": "fr_ct_gf05",
      "name": "Environmental Protection",
      "name_fr": "Protection de l'environnement",
      "value": 17731800000
    },
    {
      "id": "fr_ct_gf03",
      "name": "Public Order & Safety",
      "name_fr": "Ordre et sécurité publics",
      "value": 7391500000
    },
    {
      "id": "fr_ct_gf07",
      "name": "Health",
      "name_fr": "Santé",
      "value": 1733900000
    }
  ]
}